Workbook

Sheet Summary
A1: CASPAA — School Operating System · Test Execution Summary
A3: Test Area | B3: Total | C3: Passed | D3: Failed | E3: Blocker | F3: Not-Executed | G3: % Executed
A4: M01 Students & Admissions | B4: ='M01 Students & Admissions'!F3 | C4: ='M01 Students & Admissions'!G3 | D4: ='M01 Students & Admissions'!H3 | E4: ='M01 Students & Admissions'!I3 | F4: ='M01 Students & Admissions'!J3 | G4: =IF(B4=0,0,(B4-F4)/B4)
A5: M02 Academic Management | B5: ='M02 Academic Management'!F3 | C5: ='M02 Academic Management'!G3 | D5: ='M02 Academic Management'!H3 | E5: ='M02 Academic Management'!I3 | F5: ='M02 Academic Management'!J3 | G5: =IF(B5=0,0,(B5-F5)/B5)
A6: M03 Attendance | B6: ='M03 Attendance'!F3 | C6: ='M03 Attendance'!G3 | D6: ='M03 Attendance'!H3 | E6: ='M03 Attendance'!I3 | F6: ='M03 Attendance'!J3 | G6: =IF(B6=0,0,(B6-F6)/B6)
A7: M04 Results & Reporting | B7: ='M04 Results & Reporting'!F3 | C7: ='M04 Results & Reporting'!G3 | D7: ='M04 Results & Reporting'!H3 | E7: ='M04 Results & Reporting'!I3 | F7: ='M04 Results & Reporting'!J3 | G7: =IF(B7=0,0,(B7-F7)/B7)
A8: M05 Finance & Fees (Ledger) | B8: ='M05 Finance & Fees (Ledger)'!F3 | C8: ='M05 Finance & Fees (Ledger)'!G3 | D8: ='M05 Finance & Fees (Ledger)'!H3 | E8: ='M05 Finance & Fees (Ledger)'!I3 | F8: ='M05 Finance & Fees (Ledger)'!J3 | G8: =IF(B8=0,0,(B8-F8)/B8)
A9: M06 Payments | B9: ='M06 Payments'!F3 | C9: ='M06 Payments'!G3 | D9: ='M06 Payments'!H3 | E9: ='M06 Payments'!I3 | F9: ='M06 Payments'!J3 | G9: =IF(B9=0,0,(B9-F9)/B9)
A10: M07 Staff & HR + Payroll | B10: ='M07 Staff & HR + Payroll'!F3 | C10: ='M07 Staff & HR + Payroll'!G3 | D10: ='M07 Staff & HR + Payroll'!H3 | E10: ='M07 Staff & HR + Payroll'!I3 | F10: ='M07 Staff & HR + Payroll'!J3 | G10: =IF(B10=0,0,(B10-F10)/B10)
A11: M08 Communications | B11: ='M08 Communications'!F3 | C11: ='M08 Communications'!G3 | D11: ='M08 Communications'!H3 | E11: ='M08 Communications'!I3 | F11: ='M08 Communications'!J3 | G11: =IF(B11=0,0,(B11-F11)/B11)
A12: M09 Calendar & Notice Board | B12: ='M09 Calendar & Notice Board'!F3 | C12: ='M09 Calendar & Notice Board'!G3 | D12: ='M09 Calendar & Notice Board'!H3 | E12: ='M09 Calendar & Notice Board'!I3 | F12: ='M09 Calendar & Notice Board'!J3 | G12: =IF(B12=0,0,(B12-F12)/B12)
A13: M10 House Points | B13: ='M10 House Points'!F3 | C13: ='M10 House Points'!G3 | D13: ='M10 House Points'!H3 | E13: ='M10 House Points'!I3 | F13: ='M10 House Points'!J3 | G13: =IF(B13=0,0,(B13-F13)/B13)
A14: M11 Transport & Pickup | B14: ='M11 Transport & Pickup'!F3 | C14: ='M11 Transport & Pickup'!G3 | D14: ='M11 Transport & Pickup'!H3 | E14: ='M11 Transport & Pickup'!I3 | F14: ='M11 Transport & Pickup'!J3 | G14: =IF(B14=0,0,(B14-F14)/B14)
A15: M12 Health & Sickbay | B15: ='M12 Health & Sickbay'!F3 | C15: ='M12 Health & Sickbay'!G3 | D15: ='M12 Health & Sickbay'!H3 | E15: ='M12 Health & Sickbay'!I3 | F15: ='M12 Health & Sickbay'!J3 | G15: =IF(B15=0,0,(B15-F15)/B15)
A16: M13 Alumni | B16: ='M13 Alumni'!F3 | C16: ='M13 Alumni'!G3 | D16: ='M13 Alumni'!H3 | E16: ='M13 Alumni'!I3 | F16: ='M13 Alumni'!J3 | G16: =IF(B16=0,0,(B16-F16)/B16)
A17: M14 Assessments (CBT) | B17: ='M14 Assessments (CBT)'!F3 | C17: ='M14 Assessments (CBT)'!G3 | D17: ='M14 Assessments (CBT)'!H3 | E17: ='M14 Assessments (CBT)'!I3 | F17: ='M14 Assessments (CBT)'!J3 | G17: =IF(B17=0,0,(B17-F17)/B17)
A18: M15 Multi-branch Groups | B18: ='M15 Multi-branch Groups'!F3 | C18: ='M15 Multi-branch Groups'!G3 | D18: ='M15 Multi-branch Groups'!H3 | E18: ='M15 Multi-branch Groups'!I3 | F18: ='M15 Multi-branch Groups'!J3 | G18: =IF(B18=0,0,(B18-F18)/B18)
A19: M16 Feature Entitlements | B19: ='M16 Feature Entitlements'!F3 | C19: ='M16 Feature Entitlements'!G3 | D19: ='M16 Feature Entitlements'!H3 | E19: ='M16 Feature Entitlements'!I3 | F19: ='M16 Feature Entitlements'!J3 | G19: =IF(B19=0,0,(B19-F19)/B19)
A20: M17 Super Admin (COP) | B20: ='M17 Super Admin (COP)'!F3 | C20: ='M17 Super Admin (COP)'!G3 | D20: ='M17 Super Admin (COP)'!H3 | E20: ='M17 Super Admin (COP)'!I3 | F20: ='M17 Super Admin (COP)'!J3 | G20: =IF(B20=0,0,(B20-F20)/B20)
A21: M18 Lending (On Hold) | B21: ='M18 Lending (On Hold)'!F3 | C21: ='M18 Lending (On Hold)'!G3 | D21: ='M18 Lending (On Hold)'!H3 | E21: ='M18 Lending (On Hold)'!I3 | F21: ='M18 Lending (On Hold)'!J3 | G21: =IF(B21=0,0,(B21-F21)/B21)
A22: M19 Learning & Content | B22: ='M19 Learning & Content'!F3 | C22: ='M19 Learning & Content'!G3 | D22: ='M19 Learning & Content'!H3 | E22: ='M19 Learning & Content'!I3 | F22: ='M19 Learning & Content'!J3 | G22: =IF(B22=0,0,(B22-F22)/B22)
A23: M20 Behaviour & Discipline | B23: ='M20 Behaviour & Discipline'!F3 | C23: ='M20 Behaviour & Discipline'!G3 | D23: ='M20 Behaviour & Discipline'!H3 | E23: ='M20 Behaviour & Discipline'!I3 | F23: ='M20 Behaviour & Discipline'!J3 | G23: =IF(B23=0,0,(B23-F23)/B23)
A24: M21 Messaging | B24: ='M21 Messaging'!F3 | C24: ='M21 Messaging'!G3 | D24: ='M21 Messaging'!H3 | E24: ='M21 Messaging'!I3 | F24: ='M21 Messaging'!J3 | G24: =IF(B24=0,0,(B24-F24)/B24)
A25: M22 Front Desk | B25: ='M22 Front Desk'!F3 | C25: ='M22 Front Desk'!G3 | D25: ='M22 Front Desk'!H3 | E25: ='M22 Front Desk'!I3 | F25: ='M22 Front Desk'!J3 | G25: =IF(B25=0,0,(B25-F25)/B25)
A26: M23 Operations Hub | B26: ='M23 Operations Hub'!F3 | C26: ='M23 Operations Hub'!G3 | D26: ='M23 Operations Hub'!H3 | E26: ='M23 Operations Hub'!I3 | F26: ='M23 Operations Hub'!J3 | G26: =IF(B26=0,0,(B26-F26)/B26)
A27: M24 School Store | B27: ='M24 School Store'!F3 | C27: ='M24 School Store'!G3 | D27: ='M24 School Store'!H3 | E27: ='M24 School Store'!I3 | F27: ='M24 School Store'!J3 | G27: =IF(B27=0,0,(B27-F27)/B27)
A28: M25 Settings & Branding | B28: ='M25 Settings & Branding'!F3 | C28: ='M25 Settings & Branding'!G3 | D28: ='M25 Settings & Branding'!H3 | E28: ='M25 Settings & Branding'!I3 | F28: ='M25 Settings & Branding'!J3 | G28: =IF(B28=0,0,(B28-F28)/B28)
A29: M26 Reports & Analytics | B29: ='M26 Reports & Analytics'!F3 | C29: ='M26 Reports & Analytics'!G3 | D29: ='M26 Reports & Analytics'!H3 | E29: ='M26 Reports & Analytics'!I3 | F29: ='M26 Reports & Analytics'!J3 | G29: =IF(B29=0,0,(B29-F29)/B29)
A30: M27 Audit Log | B30: ='M27 Audit Log'!F3 | C30: ='M27 Audit Log'!G3 | D30: ='M27 Audit Log'!H3 | E30: ='M27 Audit Log'!I3 | F30: ='M27 Audit Log'!J3 | G30: =IF(B30=0,0,(B30-F30)/B30)
A31: M28 Notifications | B31: ='M28 Notifications'!F3 | C31: ='M28 Notifications'!G3 | D31: ='M28 Notifications'!H3 | E31: ='M28 Notifications'!I3 | F31: ='M28 Notifications'!J3 | G31: =IF(B31=0,0,(B31-F31)/B31)
A32: M29 Help & Support | B32: ='M29 Help & Support'!F3 | C32: ='M29 Help & Support'!G3 | D32: ='M29 Help & Support'!H3 | E32: ='M29 Help & Support'!I3 | F32: ='M29 Help & Support'!J3 | G32: =IF(B32=0,0,(B32-F32)/B32)
A33: M30 Subscription & Billing | B33: ='M30 Subscription & Billing'!F3 | C33: ='M30 Subscription & Billing'!G3 | D33: ='M30 Subscription & Billing'!H3 | E33: ='M30 Subscription & Billing'!I3 | F33: ='M30 Subscription & Billing'!J3 | G33: =IF(B33=0,0,(B33-F33)/B33)
A34: M31 AI Assistant & Insights | B34: ='M31 AI Assistant & Insights'!F3 | C34: ='M31 AI Assistant & Insights'!G3 | D34: ='M31 AI Assistant & Insights'!H3 | E34: ='M31 AI Assistant & Insights'!I3 | F34: ='M31 AI Assistant & Insights'!J3 | G34: =IF(B34=0,0,(B34-F34)/B34)
A35: M32 Public Site & Acquisition | B35: ='M32 Public Site & Acquisition'!F3 | C35: ='M32 Public Site & Acquisition'!G3 | D35: ='M32 Public Site & Acquisition'!H3 | E35: ='M32 Public Site & Acquisition'!I3 | F35: ='M32 Public Site & Acquisition'!J3 | G35: =IF(B35=0,0,(B35-F35)/B35)
A36: M33 Role Dashboards | B36: ='M33 Role Dashboards'!F3 | C36: ='M33 Role Dashboards'!G3 | D36: ='M33 Role Dashboards'!H3 | E36: ='M33 Role Dashboards'!I3 | F36: ='M33 Role Dashboards'!J3 | G36: =IF(B36=0,0,(B36-F36)/B36)
A37: M34 COP Platform Settings | B37: ='M34 COP Platform Settings'!F3 | C37: ='M34 COP Platform Settings'!G3 | D37: ='M34 COP Platform Settings'!H3 | E37: ='M34 COP Platform Settings'!I3 | F37: ='M34 COP Platform Settings'!J3 | G37: =IF(B37=0,0,(B37-F37)/B37)
A38: X1 Auth & Tenancy | B38: ='X1 Auth & Tenancy'!F3 | C38: ='X1 Auth & Tenancy'!G3 | D38: ='X1 Auth & Tenancy'!H3 | E38: ='X1 Auth & Tenancy'!I3 | F38: ='X1 Auth & Tenancy'!J3 | G38: =IF(B38=0,0,(B38-F38)/B38)
A39: X2 Offline & PWA | B39: ='X2 Offline & PWA'!F3 | C39: ='X2 Offline & PWA'!G3 | D39: ='X2 Offline & PWA'!H3 | E39: ='X2 Offline & PWA'!I3 | F39: ='X2 Offline & PWA'!J3 | G39: =IF(B39=0,0,(B39-F39)/B39)
A40: X3 Usability & Accessibility | B40: ='X3 Usability & Accessibility'!F3 | C40: ='X3 Usability & Accessibility'!G3 | D40: ='X3 Usability & Accessibility'!H3 | E40: ='X3 Usability & Accessibility'!I3 | F40: ='X3 Usability & Accessibility'!J3 | G40: =IF(B40=0,0,(B40-F40)/B40)
A41: TOTAL | B41: =SUM(B4:B40) | C41: =SUM(C4:C40) | D41: =SUM(D4:D40) | E41: =SUM(E4:E40) | F41: =SUM(F4:F40) | G41: =IF(B41=0,0,(B41-F41)/B41)
A44: Status legend
A45: Not-Executed | B45: Written but not yet run in this cycle.
A46: Passed | B46: Actual result matched the expected result.
A47: Failed | B47: Actual result differed. Log a defect and reference it in Comment.
A48: Blocker | B48: Could not be executed — a defect or missing data blocks the path.
A49: N/A | B49: Not applicable to this build, plan tier or platform.
A52: How to use this workbook
A53: 1. Upload to Google Drive and open with Google Sheets — tabs, dropdowns and colour rules are preserved.
A54: 2. Tabs M01-M34 map one-to-one onto the modules in CASPAA_PRD_v4.md (v4.1). X1-X3 are cross-cutting suites.
A55: 3. Work one tab at a time. Set Status from the dropdown in column C; the counters in F3:J3 update live.
A56: 4. Record a defect ID and a one-line observation in Comment for every Failed or Blocker.
A57: 5. This Summary rolls up every scenario tab automatically — do not overwrite its formulas.
A58: 6. 'Test Cases (Detailed)' holds step-level cases for the highest-risk flow in each module.
A59: 7. M18 Lending is ON HOLD: those scenarios assert the feature stays unreachable, and all should pass.
A60: 8. Re-baseline by setting every Status back to Not-Executed at the start of each regression cycle.

Sheet M01 Students & Admissions
A1: S/N | B1: Test Scenario | C1: Status | D1: Comment | F1: CASPAA — Web / PWA · M01 Students & Admissions
A2: 1 | B2: Verify that a student can be added with name, DOB, gender, class, house, admission number, photo and parent link. | C2: Not-Executed | F2: Total test scenarios | G2: Pass | H2: Fail | I2: Blocker | J2: Not-Executed
A3: 2 | B3: Verify that a duplicate admission number is rejected with a clear error and the student is not saved. | C3: Not-Executed | F3: =COUNTA(B2:B21) | G3: =COUNTIF(C2:C21,"Passed") | H3: =COUNTIF(C2:C21,"Failed") | I3: =COUNTIF(C2:C21,"Blocker") | J3: =COUNTIF(C2:C21,"Not-Executed")
A4: 3 | B4: Verify that a newly added student appears immediately in the class roster, attendance register and fee module. | C4: Not-Executed
A5: 4 | B5: Verify that the linked parent receives an in-app notification when their child is registered. | C5: Not-Executed
A6: 5 | B6: Verify that a CSV bulk import previews the parsed rows before anything is committed. | C6: Not-Executed
A7: 6 | B7: Verify that invalid CSV rows are flagged with a specific reason while the valid rows still import. | C7: Not-Executed
A8: 7 | B8: Verify that one bad row in a CSV never blocks the import of the remaining rows. | C8: Not-Executed
A9: 8 | B9: Verify that an online admission application can be accepted and converts into an enrolled student. | C9: Not-Executed
A10: 9 | B10: Verify that an admission application can be rejected with a reason recorded. | C10: Not-Executed
A11: 10 | B11: Verify that the Returning Student flow restores the prior record instead of creating a duplicate. | C11: Not-Executed
A12: 11 | B12: Verify that bulk promotion moves an entire class to the next class in one action. | C12: Not-Executed
A13: 12 | B13: Verify that graduating a class sets status to alumni and removes them from active rosters. | C13: Not-Executed
A14: 13 | B14: Verify that a graduated student's ledger and academic history remain fully intact. | C14: Not-Executed
A15: 14 | B15: Verify that deactivating a student hides them from active rosters but preserves their records. | C15: Not-Executed
... A21: 20 | B21: Verify that a student photo upload rejects unsupported formats with a clear message. | C21: Not-Executed

Sheet M02 Academic Management
A1: S/N | B1: Test Scenario | C1: Status | D1: Comment | F1: CASPAA — Web / PWA · M02 Academic Management
A2: 1 | B2: Verify that the academic session, terms and holidays can be defined in the calendar. | C2: Not-Executed | F2: Total test scenarios | G2: Pass | H2: Fail | I2: Blocker | J2: Not-Executed
A3: 2 | B3: Verify that term dates set here drive scheduling across every other module. | C3: Not-Executed | F3: =COUNTA(B2:B18) | G3: =COUNTIF(C2:C18,"Passed") | H3: =COUNTIF(C2:C18,"Failed") | I3: =COUNTIF(C2:C18,"Blocker") | J3: =COUNTIF(C2:C18,"Not-Executed")
A4: 3 | B4: Verify that class arms can be created under a parent class. | C4: Not-Executed
A5: 4 | B5: Verify that a subject can be added to the curriculum for a specific class. | C5: Not-Executed
A6: 5 | B6: Verify that the timetable can be built with periods per class per day. | C6: Not-Executed
A7: 6 | B7: Verify that a timetable clash for the same teacher in two places is surfaced. | C7: Not-Executed
A8: 7 | B8: Verify that the published timetable is visible to the assigned teachers. | C8: Not-Executed
A9: 8 | B9: Verify that the published timetable is visible to the students of that class. | C9: Not-Executed
A10: 9 | B10: Verify that a scheme of work can be added per subject per term. | C10: Not-Executed
A11: 10 | B11: Verify that the assessment structure sets the CA and exam weighting used by results. | C11: Not-Executed
A12: 11 | B12: Verify that grade boundaries configured here are applied when grades are computed. | C12: Not-Executed
A13: 12 | B13: Verify that the results broadsheet ranks students by average automatically. | C13: Not-Executed
A14: 13 | B14: Verify that the broadsheet figures match the individual report cards exactly. | C14: Not-Executed
A15: 14 | B15: Verify that a class with no timetable shows an empty state rather than an error. | C15: Not-Executed
... A18: 17 | B18: Verify that a subject can be assigned to a teacher and appears in their class list. | C18: Not-Executed

Sheet M03 Attendance
A1: S/N | B1: Test Scenario | C1: Status | D1: Comment | F1: CASPAA — Web / PWA · M03 Attendance
A2: 1 | B2: Verify that a teacher can open their class and every student defaults to Present. | C2: Not-Executed | F2: Total test scenarios | G2: Pass | H2: Fail | I2: Blocker | J2: Not-Executed
A3: 2 | B3: Verify that today's date is auto-filled on the attendance screen. | C3: Not-Executed | F3: =COUNTA(B2:B17) | G3: =COUNTIF(C2:C17,"Passed") | H3: =COUNTIF(C2:C17,"Failed") | I3: =COUNTIF(C2:C17,"Blocker") | J3: =COUNTIF(C2:C17,"Not-Executed")
A4: 3 | B4: Verify that a student can be toggled between Present, Absent and Late. | C4: Not-Executed
A5: 4 | B5: Verify that a Late mark is recorded and reported distinctly from Absent. | C5: Not-Executed
A6: 5 | B6: Verify that submitting attendance saves it against schoolId, classId, date and teacher. | C6: Not-Executed
A7: 6 | B7: Verify that the same class and date cannot be submitted twice without an admin override. | C7: Not-Executed
A8: 7 | B8: Verify that parents of absent students receive an alert the same day. | C8: Not-Executed
A9: 8 | B9: Verify that the attendance percentage per class and per day is calculated correctly. | C9: Not-Executed
A10: 9 | B10: Verify that a parent can see only their own child's attendance record. | C10: Not-Executed
A11: 10 | B11: Verify that attendance marked while offline is stored locally and syncs on reconnect. | C11: Not-Executed
A12: 11 | B12: Verify that an offline submission which later syncs does not create a duplicate record. | C12: Not-Executed
A13: 12 | B13: Verify that a teacher can take attendance only for classes assigned to them. | C13: Not-Executed
A14: 13 | B14: Verify that an admin can view school-wide and per-class attendance rates. | C14: Not-Executed
A15: 14 | B15: Verify that a class with no students shows an empty state rather than an error. | C15: Not-Executed
... A17: 16 | B17: Verify that a student absent three consecutive days raises the at-risk insight. | C17: Not-Executed

Sheet M04 Results & Reporting
A1: S/N | B1: Test Scenario | C1: Status | D1: Comment | F1: CASPAA — Web / PWA · M04 Results & Reporting
A2: 1 | B2: Verify that a teacher can enter CA and exam scores for every student in a subject. | C2: Not-Executed | F2: Total test scenarios | G2: Pass | H2: Fail | I2: Blocker | J2: Not-Executed
A3: 2 | B3: Verify that the total is auto-computed as CA plus Exam. | C3: Not-Executed | F3: =COUNTA(B2:B19) | G3: =COUNTIF(C2:C19,"Passed") | H3: =COUNTIF(C2:C19,"Failed") | I3: =COUNTIF(C2:C19,"Blocker") | J3: =COUNTIF(C2:C19,"Not-Executed")
A4: 3 | B4: Verify that the grade assigned matches the configured grade boundaries. | C4: Not-Executed
A5: 4 | B5: Verify that a score above the configured maximum is rejected. | C5: Not-Executed
A6: 5 | B6: Verify that a negative or non-numeric score is rejected. | C6: Not-Executed
A7: 6 | B7: Verify that submitting results marks them pending approval and not yet visible downstream. | C7: Not-Executed
A8: 7 | B8: Verify that pending results are not visible to parents or students in any view. | C8: Not-Executed
A9: 8 | B9: Verify that a parent or student sees a pending banner while results await approval. | C9: Not-Executed
A10: 9 | B10: Verify that Approve is disabled while any student is missing the required comment. | C10: Not-Executed
A11: 10 | B11: Verify that approving results notifies parents and students exactly once. | C11: Not-Executed
A12: 11 | B12: Verify that the broadsheet is ranked by average score. | C12: Not-Executed
A13: 12 | B13: Verify that tied averages share a rank and the next rank skips accordingly. | C13: Not-Executed
A14: 13 | B14: Verify that an approved report card can be printed with the school's branding. | C14: Not-Executed
A15: 14 | B15: Verify that printed report card figures match the broadsheet exactly. | C15: Not-Executed
... A19: 18 | B19: Verify that approval is atomic per class and subject. | C19: Not-Executed

Sheet M05 Finance & Fees (Ledger)
A1: S/N | B1: Test Scenario | C1: Status | D1: Comment | F1: CASPAA — Web / PWA · M05 Finance & Fees (Ledger)
A2: 1 | B2: Verify that a fee structure can be set per class and per term. | C2: Not-Executed | F2: Total test scenarios | G2: Pass | H2: Fail | I2: Blocker | J2: Not-Executed
A3: 2 | B3: Verify that bulk invoice generation creates exactly one invoice per active student. | C3: Not-Executed | F3: =COUNTA(B2:B25) | G3: =COUNTIF(C2:C25,"Passed") | H3: =COUNTIF(C2:C25,"Failed") | I3: =COUNTIF(C2:C25,"Blocker") | J3: =COUNTIF(C2:C25,"Not-Executed")
A4: 3 | B4: Verify that the generated invoice count matches the number of active students. | C4: Not-Executed
A5: 4 | B5: Verify that parents are notified once invoices are generated. | C5: Not-Executed
A6: 5 | B6: Verify that the student ledger shows each charge, discount and payment as its own dated row. | C6: Not-Executed
A7: 6 | B7: Verify that no charges, discounts or payments are lumped into a single combined line. | C7: Not-Executed
A8: 7 | B8: Verify that the opening balance is carried forward as its own labelled row. | C8: Not-Executed
A9: 8 | B9: Verify that the running balance is correct after every transaction on the ledger. | C9: Not-Executed
A10: 9 | B10: Verify that the invariant debit total minus credit total equals the balance for every student. | C10: Not-Executed
A11: 10 | B11: Verify that an overpayment is shown as a credit balance labelled Cr. | C11: Not-Executed
A12: 11 | B12: Verify that credit is auto-applied to the next invoice and the parent is notified. | C12: Not-Executed
A13: 12 | B13: Verify that sibling, bus and special discounts each appear as separate credit lines. | C13: Not-Executed
A14: 13 | B14: Verify that discounts and opening balances never double-count against invoice totals. | C14: Not-Executed
A15: 14 | B15: Verify that adding a line item to a bill recomputes total, balance and status. | C15: Not-Executed
... A25: 24 | B25: Verify that every money action writes an immutable audit log entry. | C25: Not-Executed

Sheet M06 Payments
A1: S/N | B1: Test Scenario | C1: Status | D1: Comment | F1: CASPAA — Web / PWA · M06 Payments
A2: 1 | B2: Verify that a parent can pay an invoice by card. | C2: Not-Executed | F2: Total test scenarios | G2: Pass | H2: Fail | I2: Blocker | J2: Not-Executed
A3: 2 | B3: Verify that a parent can pay an invoice by bank transfer. | C3: Not-Executed | F3: =COUNTA(B2:B17) | G3: =COUNTIF(C2:C17,"Passed") | H3: =COUNTIF(C2:C17,"Failed") | I3: =COUNTIF(C2:C17,"Blocker") | J3: =COUNTIF(C2:C17,"Not-Executed")
A4: 3 | B4: Verify that a parent can pay an invoice by USSD. | C4: Not-Executed
A5: 4 | B5: Verify that a successful payment marks the invoice Paid and clears the balance. | C5: Not-Executed
A6: 5 | B6: Verify that a partial payment leaves the correct remaining balance and a part-paid status. | C6: Not-Executed
A7: 6 | B7: Verify that a receipt is available in the parent portal immediately after payment. | C7: Not-Executed
A8: 7 | B8: Verify that a receipt can be viewed, printed or downloaded at any time afterwards. | C8: Not-Executed
A9: 8 | B9: Verify that a failed payment is logged with its reason and is visible to finance. | C9: Not-Executed
A10: 9 | B10: Verify that a double-submitted payment never charges or credits twice. | C10: Not-Executed
A11: 10 | B11: Verify that a payment attempted offline queues and does not duplicate on reconnect. | C11: Not-Executed
A12: 11 | B12: Verify that multi-child Pay All processes each invoice in sequence with a method per child. | C12: Not-Executed
A13: 12 | B13: Verify that every payment is persisted with a unique gateway reference. | C13: Not-Executed
A14: 13 | B14: Verify that a parent cannot pay another family's invoice by altering the invoice ID. | C14: Not-Executed
A15: 14 | B15: Verify that the finance payments list reflects a new transaction immediately. | C15: Not-Executed
... A17: 16 | B17: Verify that a refund is recorded as its own ledger movement and audited. | C17: Not-Executed

Sheet M07 Staff & HR + Payroll
A1: S/N | B1: Test Scenario | C1: Status | D1: Comment | F1: CASPAA — Web / PWA · M07 Staff & HR + Payroll
A2: 1 | B2: Verify that a staff profile can be created with role, subjects and class assignments. | C2: Not-Executed | F2: Total test scenarios | G2: Pass | H2: Fail | I2: Blocker | J2: Not-Executed
A3: 2 | B3: Verify that staff attendance can be recorded for a given day. | C3: Not-Executed | F3: =COUNTA(B2:B26) | G3: =COUNTIF(C2:C26,"Passed") | H3: =COUNTIF(C2:C26,"Failed") | I3: =COUNTIF(C2:C26,"Blocker") | J3: =COUNTIF(C2:C26,"Not-Executed")
A4: 3 | B4: Verify that a teacher can submit a leave request with dates and a reason. | C4: Not-Executed
A5: 4 | B5: Verify that an admin can approve or decline a leave request with a note. | C5: Not-Executed
A6: 5 | B6: Verify that the leave request badge count matches the pending requests. | C6: Not-Executed
A7: 6 | B7: Verify that the teacher is notified of the leave outcome. | C7: Not-Executed
A8: 7 | B8: Verify that approved leave is reflected in the attendance register. | C8: Not-Executed
A9: 8 | B9: Verify that leave balances decrement correctly on approval. | C9: Not-Executed
A10: 9 | B10: Verify that a salary advance can be requested with an amount and repayment months. | C10: Not-Executed
A11: 10 | B11: Verify that an approved advance creates a deduction schedule. | C11: Not-Executed
A12: 11 | B12: Verify that advance deductions apply automatically in each payroll run until cleared. | C12: Not-Executed
A13: 12 | B13: Verify that an advance can never over-deduct beyond its outstanding balance. | C13: Not-Executed
A14: 13 | B14: Verify that a payroll run loads only active staff. | C14: Not-Executed
A15: 14 | B15: Verify that terminated or inactive staff are excluded from the run. | C15: Not-Executed
... A26: 25 | B26: Verify that a substitute assignment is visible on the affected class. | C26: Not-Executed

Sheet M08 Communications
A1: S/N | B1: Test Scenario | C1: Status | D1: Comment | F1: CASPAA — Web / PWA · M08 Communications
A2: 1 | B2: Verify that an announcement can be sent to a targeted audience. | C2: Not-Executed | F2: Total test scenarios | G2: Pass | H2: Fail | I2: Blocker | J2: Not-Executed
A3: 2 | B3: Verify that only the targeted role receives and can see the announcement. | C3: Not-Executed | F3: =COUNTA(B2:B20) | G3: =COUNTIF(C2:C20,"Passed") | H3: =COUNTIF(C2:C20,"Failed") | I3: =COUNTIF(C2:C20,"Blocker") | J3: =COUNTIF(C2:C20,"Not-Executed")
A4: 3 | B4: Verify that a notice can be posted to the notice board and appears newest first. | C4: Not-Executed
A5: 4 | B5: Verify that a consent form can be created with a title, deadline and audience. | C5: Not-Executed
A6: 5 | B6: Verify that parents are notified when a consent form is published. | C6: Not-Executed
A7: 6 | B7: Verify that a parent can agree or decline with an optional reason. | C7: Not-Executed
A8: 7 | B8: Verify that a parent cannot submit a consent response twice. | C8: Not-Executed
A9: 8 | B9: Verify that the admin response tally updates without a page refresh. | C9: Not-Executed
A10: 9 | B10: Verify that a consent form auto-closes after its deadline and rejects late responses. | C10: Not-Executed
A11: 10 | B11: Verify that deadline enforcement holds even if the client device clock is changed. | C11: Not-Executed
A12: 11 | B12: Verify that a survey can be created and its results aggregated. | C12: Not-Executed
A13: 12 | B13: Verify that survey results can be exported. | C13: Not-Executed
A14: 13 | B14: Verify that a teacher can write a diary note the linked parent can read. | C14: Not-Executed
A15: 14 | B15: Verify that a parent can reply to a diary note and the thread stays ordered. | C15: Not-Executed
... A20: 19 | B20: Verify that outbound sends respect the school's channel configuration. | C20: Not-Executed

Sheet M09 Calendar & Notice Board
A1: S/N | B1: Test Scenario | C1: Status | D1: Comment | F1: CASPAA — Web / PWA · M09 Calendar & Notice Board
A2: 1 | B2: Verify that an admin can add a dated event with a title, type and audience. | C2: Not-Executed | F2: Total test scenarios | G2: Pass | H2: Fail | I2: Blocker | J2: Not-Executed
A3: 2 | B3: Verify that the event appears only on the targeted audience's calendar. | C3: Not-Executed | F3: =COUNTA(B2:B15) | G3: =COUNTIF(C2:C15,"Passed") | H3: =COUNTIF(C2:C15,"Failed") | I3: =COUNTIF(C2:C15,"Blocker") | J3: =COUNTIF(C2:C15,"Not-Executed")
A4: 3 | B4: Verify that a multi-day event is shown across every affected day. | C4: Not-Executed
A5: 4 | B5: Verify that a teacher or parent sees the calendar as view-only. | C5: Not-Executed
A6: 5 | B6: Verify that create, edit and delete are gated to admin and principal. | C6: Not-Executed
A7: 6 | B7: Verify that a day with no events shows a No events state. | C7: Not-Executed
A8: 7 | B8: Verify that an event can be edited and the change reflects for all audiences. | C8: Not-Executed
A9: 8 | B9: Verify that a deleted event disappears from every calendar view. | C9: Not-Executed
A10: 9 | B10: Verify that the calendar reads its term dates from School Settings only. | C10: Not-Executed
A11: 10 | B11: Verify that an unconfigured calendar prompts the admin to configure term dates. | C11: Not-Executed
A12: 11 | B12: Verify that a non-admin sees an explanatory message rather than a configure button. | C12: Not-Executed
A13: 12 | B13: Verify that notices are pinned and ordered newest first. | C13: Not-Executed
A14: 13 | B14: Verify that a notice audience filter hides it from non-targeted roles. | C14: Not-Executed
A15: 14 | B15: Verify that calendar events are scoped to the active branch. | C15: Not-Executed

Sheet M10 House Points
A1: S/N | B1: Test Scenario | C1: Status | D1: Comment | F1: CASPAA — Web / PWA · M10 House Points
A2: 1 | B2: Verify that a teacher can award points to a student with a reason. | C2: Not-Executed | F2: Total test scenarios | G2: Pass | H2: Fail | I2: Blocker | J2: Not-Executed
A3: 2 | B3: Verify that a teacher can deduct points with a reason. | C3: Not-Executed | F3: =COUNTA(B2:B15) | G3: =COUNTIF(C2:C15,"Passed") | H3: =COUNTIF(C2:C15,"Failed") | I3: =COUNTIF(C2:C15,"Blocker") | J3: =COUNTIF(C2:C15,"Not-Executed")
A4: 3 | B4: Verify that awarding without a reason is rejected. | C4: Not-Executed
A5: 4 | B5: Verify that the house total updates immediately on save. | C5: Not-Executed
A6: 5 | B6: Verify that the student and their parent are notified of an award. | C6: Not-Executed
A7: 6 | B7: Verify that an inter-house competition result can be recorded by position. | C7: Not-Executed
A8: 7 | B8: Verify that competition points award 1st=50, 2nd=35, 3rd=20 and 4th=10. | C8: Not-Executed
A9: 8 | B9: Verify that the leaderboard sorts houses by combined merit and competition totals. | C9: Not-Executed
A10: 9 | B10: Verify that the leaderboard shows the merit and competition breakdown separately. | C10: Not-Executed
A11: 10 | B11: Verify that per-student point history is viewable and attributable to its author. | C11: Not-Executed
A12: 11 | B12: Verify that a student sees their own house standing. | C12: Not-Executed
A13: 12 | B13: Verify that a parent sees their child's house standing. | C13: Not-Executed
A14: 13 | B14: Verify that a merit recorded in Behaviour can feed house points. | C14: Not-Executed
A15: 14 | B15: Verify that house points are scoped to the active branch. | C15: Not-Executed

Sheet M11 Transport & Pickup
A1: S/N | B1: Test Scenario | C1: Status | D1: Comment | F1: CASPAA — Web / PWA · M11 Transport & Pickup
A2: 1 | B2: Verify that a bus route can be created with a driver and vehicle. | C2: Not-Executed | F2: Total test scenarios | G2: Pass | H2: Fail | I2: Blocker | J2: Not-Executed
A3: 2 | B3: Verify that students can be assigned to a route. | C3: Not-Executed | F3: =COUNTA(B2:B17) | G3: =COUNTIF(C2:C17,"Passed") | H3: =COUNTIF(C2:C17,"Failed") | I3: =COUNTIF(C2:C17,"Blocker") | J3: =COUNTIF(C2:C17,"Not-Executed")
A4: 3 | B4: Verify that each route is managed independently of the others. | C4: Not-Executed
A5: 4 | B5: Verify that the transport officer can set bus status to Departed. | C5: Not-Executed
A6: 5 | B6: Verify that setting Delayed accepts an explanatory note. | C6: Not-Executed
A7: 6 | B7: Verify that setting Arrived notifies parents on that route within seconds. | C7: Not-Executed
A8: 7 | B8: Verify that only parents of students on that route are notified. | C8: Not-Executed
A9: 8 | B9: Verify that a colour-coded status pill shows on the parent's transport card. | C9: Not-Executed
A10: 9 | B10: Verify that the status pill is distinguishable without relying on colour alone. | C10: Not-Executed
A11: 10 | B11: Verify that a parent can add an authorised pickup person for approval. | C11: Not-Executed
A12: 11 | B12: Verify that an admin can approve or deny an authorised pickup person. | C12: Not-Executed
A13: 12 | B13: Verify that an approved pickup person appears in the child's pickup list. | C13: Not-Executed
A14: 13 | B14: Verify that a revoked pickup person is removed immediately. | C14: Not-Executed
A15: 14 | B15: Verify that the gate check reflects the current approved pickup list. | C15: Not-Executed
... A17: 16 | B17: Verify that a deep link to Transport shows a locked screen when unentitled. | C17: Not-Executed

Sheet M12 Health & Sickbay
A1: S/N | B1: Test Scenario | C1: Status | D1: Comment | F1: CASPAA — Web / PWA · M12 Health & Sickbay
A2: 1 | B2: Verify that a sickbay visit can be logged with complaint, treatment and outcome. | C2: Not-Executed | F2: Total test scenarios | G2: Pass | H2: Fail | I2: Blocker | J2: Not-Executed
A3: 2 | B3: Verify that each visit is stamped with the date and time. | C3: Not-Executed | F3: =COUNTA(B2:B13) | G3: =COUNTIF(C2:C13,"Passed") | H3: =COUNTIF(C2:C13,"Failed") | I3: =COUNTIF(C2:C13,"Blocker") | J3: =COUNTIF(C2:C13,"Not-Executed")
A4: 3 | B4: Verify that an outcome of Sent Home forces a parent notification. | C4: Not-Executed
A5: 4 | B5: Verify that an outcome of Referred forces a parent notification. | C5: Not-Executed
A6: 5 | B6: Verify that a forced notification fires even when the notify checkbox is unchecked. | C6: Not-Executed
A7: 6 | B7: Verify that a mandatory-notification visit cannot be saved if the notification does not fire. | C7: Not-Executed
A8: 7 | B8: Verify that a routine outcome does not force a parent notification. | C8: Not-Executed
A9: 8 | B9: Verify that a parent sees their own child's visit history newest first. | C9: Not-Executed
A10: 9 | B10: Verify that a parent cannot see another child's health records. | C10: Not-Executed
A11: 10 | B11: Verify that health staff can view the full sickbay log for the school. | C11: Not-Executed
A12: 11 | B12: Verify that health records are scoped to the active branch. | C12: Not-Executed
A13: 12 | B13: Verify that the sickbay log shows an empty state when no visits exist. | C13: Not-Executed

Sheet M13 Alumni
A1: S/N | B1: Test Scenario | C1: Status | D1: Comment | F1: CASPAA — Web / PWA · M13 Alumni
A2: 1 | B2: Verify that a single student can be graduated with year, final class, exam and awards. | C2: Not-Executed | F2: Total test scenarios | G2: Pass | H2: Fail | I2: Blocker | J2: Not-Executed
A3: 2 | B3: Verify that a whole class can be graduated in one bulk action. | C3: Not-Executed | F3: =COUNTA(B2:B12) | G3: =COUNTIF(C2:C12,"Passed") | H3: =COUNTIF(C2:C12,"Failed") | I3: =COUNTIF(C2:C12,"Blocker") | J3: =COUNTIF(C2:C12,"Not-Executed")
A4: 3 | B4: Verify that graduated students are removed from active attendance, results and fees. | C4: Not-Executed
A5: 4 | B5: Verify that a graduated student's full history is preserved. | C5: Not-Executed
A6: 5 | B6: Verify that an alumnus record can be enriched with university or employer details. | C6: Not-Executed
A7: 6 | B7: Verify that a leaving certificate can be printed with school branding. | C7: Not-Executed
A8: 7 | B8: Verify that a returning alumnus can be re-admitted to active status. | C8: Not-Executed
A9: 8 | B9: Verify that re-admission preserves the prior record and does not duplicate it. | C9: Not-Executed
A10: 9 | B10: Verify that graduation and re-admission both write audit log entries. | C10: Not-Executed
A11: 10 | B11: Verify that the alumni list is searchable and filterable by graduation year. | C11: Not-Executed
A12: 11 | B12: Verify that alumni are excluded from invoice generation. | C12: Not-Executed

Sheet M14 Assessments (CBT)
A1: S/N | B1: Test Scenario | C1: Status | D1: Comment | F1: CASPAA — Web / PWA · M14 Assessments (CBT)
A2: 1 | B2: Verify that a teacher can create an assignment with a due date and class. | C2: Not-Executed | F2: Total test scenarios | G2: Pass | H2: Fail | I2: Blocker | J2: Not-Executed
A3: 2 | B3: Verify that a student can submit text, image or PDF work. | C3: Not-Executed | F3: =COUNTA(B2:B19) | G3: =COUNTIF(C2:C19,"Passed") | H3: =COUNTIF(C2:C19,"Failed") | I3: =COUNTIF(C2:C19,"Blocker") | J3: =COUNTIF(C2:C19,"Not-Executed")
A4: 3 | B4: Verify that a teacher can place an inline comment pin on an image submission. | C4: Not-Executed
A5: 4 | B5: Verify that a comment pin persists at the exact coordinates when reopened. | C5: Not-Executed
A6: 5 | B6: Verify that a PDF submission supports sidebar comments. | C6: Not-Executed
A7: 6 | B7: Verify that a teacher can set a score and a status of Excellent, Satisfactory or Needs Revision. | C7: Not-Executed
A8: 7 | B8: Verify that returning work notifies both the student and the parent. | C8: Not-Executed
A9: 8 | B9: Verify that a student can view the grade, status and inline comments. | C9: Not-Executed
A10: 9 | B10: Verify that returned work can always be resubmitted. | C10: Not-Executed
A11: 10 | B11: Verify that the resubmission modal pre-populates the previous answer. | C11: Not-Executed
A12: 11 | B12: Verify that a resubmission replaces the prior submission for re-marking. | C12: Not-Executed
A13: 12 | B13: Verify that the teacher is notified of a resubmission. | C13: Not-Executed
A14: 13 | B14: Verify that a CBT with MCQ and True or False questions auto-grades on submit. | C14: Not-Executed
A15: 14 | B15: Verify that short-answer questions remain pending until the teacher marks them. | C15: Not-Executed
... A19: 18 | B19: Verify that an assignment with no submissions shows an empty state. | C19: Not-Executed

Sheet M15 Multi-branch Groups
A1: S/N | B1: Test Scenario | C1: Status | D1: Comment | F1: CASPAA — Web / PWA · M15 Multi-branch Groups
A2: 1 | B2: Verify that a standalone school can be promoted to group HQ when entitled. | C2: Not-Executed | F2: Total test scenarios | G2: Pass | H2: Fail | I2: Blocker | J2: Not-Executed
A3: 2 | B3: Verify that promoting to HQ creates the group and preserves existing school data. | C3: Not-Executed | F3: =COUNTA(B2:B14) | G3: =COUNTIF(C2:C14,"Passed") | H3: =COUNTIF(C2:C14,"Failed") | I3: =COUNTIF(C2:C14,"Blocker") | J3: =COUNTIF(C2:C14,"Not-Executed")
A4: 3 | B4: Verify that the Branches navigation is hidden when the multibranch entitlement is off. | C4: Not-Executed
A5: 4 | B5: Verify that group overview totals equal the sum of the individual branch figures. | C5: Not-Executed
A6: 5 | B6: Verify that group enrolment equals the sum of branch enrolment. | C6: Not-Executed
A7: 6 | B7: Verify that a group owner can switch into any branch and operate it normally. | C7: Not-Executed
A8: 7 | B8: Verify that currentSchoolId resolves to the active branch after switching. | C8: Not-Executed
A9: 8 | B9: Verify that no record from one branch is visible in another after switching. | C9: Not-Executed
A10: 9 | B10: Verify that a newly added branch starts empty and fully isolated. | C10: Not-Executed
A11: 10 | B11: Verify that a branch can be added self-serve without support intervention. | C11: Not-Executed
A12: 11 | B12: Verify that the group layer stays available while switched into a branch. | C12: Not-Executed
A13: 12 | B13: Verify that the active branch is clearly shown in the header at all times. | C13: Not-Executed
A14: 13 | B14: Verify that reports and audit logs cover only the active branch. | C14: Not-Executed

Sheet M16 Feature Entitlements
A1: S/N | B1: Test Scenario | C1: Status | D1: Comment | F1: CASPAA — Web / PWA · M16 Feature Entitlements
A2: 1 | B2: Verify that features included in the plan tier are visible by default. | C2: Not-Executed | F2: Total test scenarios | G2: Pass | H2: Fail | I2: Blocker | J2: Not-Executed
A3: 2 | B3: Verify that a per-school override switches a feature on immediately. | C3: Not-Executed | F3: =COUNTA(B2:B14) | G3: =COUNTIF(C2:C14,"Passed") | H3: =COUNTIF(C2:C14,"Failed") | I3: =COUNTIF(C2:C14,"Blocker") | J3: =COUNTIF(C2:C14,"Not-Executed")
A4: 3 | B4: Verify that a per-school removal hides a feature the plan would otherwise include. | C4: Not-Executed
A5: 4 | B5: Verify that an unentitled module is hidden from the navigation entirely. | C5: Not-Executed
A6: 5 | B6: Verify that deep-linking to an unentitled view shows a locked screen. | C6: Not-Executed
A7: 6 | B7: Verify that the locked screen presents an upgrade path. | C7: Not-Executed
A8: 7 | B8: Verify that requesting a feature raises a ticket in the COP support desk. | C8: Not-Executed
A9: 8 | B9: Verify that the requesting school sees that ticket in their own Help and Support. | C9: Not-Executed
A10: 9 | B10: Verify that hasFeature resolves override before plan default. | C10: Not-Executed
A11: 10 | B11: Verify that gating is enforced in both the nav and the view guard. | C11: Not-Executed
A12: 11 | B12: Verify that every lending entry point is unreachable while the lending entitlement is off. | C12: Not-Executed
A13: 12 | B13: Verify that a global platform flag switched off overrides any per-school override. | C13: Not-Executed
A14: 13 | B14: Verify that entitlement changes take effect without a redeploy or re-login. | C14: Not-Executed

Sheet M17 Super Admin (COP)
A1: S/N | B1: Test Scenario | C1: Status | D1: Comment | F1: CASPAA — Web / PWA · M17 Super Admin (COP)
A2: 1 | B2: Verify that a new school can be created with details, plan and feature modules. | C2: Not-Executed | F2: Total test scenarios | G2: Pass | H2: Fail | I2: Blocker | J2: Not-Executed
A3: 2 | B3: Verify that a unique school ID and admin credentials are generated on creation. | C3: Not-Executed | F3: =COUNTA(B2:B20) | G3: =COUNTIF(C2:C20,"Passed") | H3: =COUNTIF(C2:C20,"Failed") | I3: =COUNTIF(C2:C20,"Blocker") | J3: =COUNTIF(C2:C20,"Not-Executed")
A4: 3 | B4: Verify that the onboarding email is sent and the status is set to Onboarding. | C4: Not-Executed
A5: 4 | B5: Verify that completing configuration moves the school status to Active. | C5: Not-Executed
A6: 5 | B6: Verify that the verification queue lists self-registered schools awaiting review. | C6: Not-Executed
A7: 6 | B7: Verify that approving a school lifts its verification gate. | C7: Not-Executed
A8: 7 | B8: Verify that rejecting a school records a reason shown verbatim to the proprietor. | C8: Not-Executed
A9: 8 | B9: Verify that suspending a school blocks all its school-side logins immediately. | C9: Not-Executed
A10: 9 | B10: Verify that reactivating a suspended school restores access. | C10: Not-Executed
A11: 10 | B11: Verify that revenue figures show MRR, ARR and commissions correctly. | C11: Not-Executed
A12: 11 | B12: Verify that a support ticket shows an SLA countdown. | C12: Not-Executed
A13: 12 | B13: Verify that a ticket breaching its SLA auto-escalates. | C13: Not-Executed
A14: 13 | B14: Verify that a COP user sees only the modules their RBAC role permits. | C14: Not-Executed
A15: 14 | B15: Verify that COP activity logs are immutable. | C15: Not-Executed
... A20: 19 | B20: Verify that every COP action is audited and attributed. | C20: Not-Executed

Sheet M18 Lending (On Hold)
A1: S/N | B1: Test Scenario | C1: Status | D1: Comment | F1: M18 Lending (On Hold) — ON HOLD, must remain gated off
A2: 1 | B2: Verify that the Lending navigation item is absent for every school. | C2: Not-Executed | F2: Total test scenarios | G2: Pass | H2: Fail | I2: Blocker | J2: Not-Executed
A3: 2 | B3: Verify that the parent Apply for a loan entry point is unreachable. | C3: Not-Executed | F3: =COUNTA(B2:B9) | G3: =COUNTIF(C2:C9,"Passed") | H3: =COUNTIF(C2:C9,"Failed") | I3: =COUNTIF(C2:C9,"Blocker") | J3: =COUNTIF(C2:C9,"Not-Executed")
A4: 3 | B4: Verify that the finance Lending view is unreachable by deep link. | C4: Not-Executed
A5: 4 | B5: Verify that the COP disbursement console is hidden or disabled. | C5: Not-Executed
A6: 5 | B6: Verify that the lending entitlement is off by default for all schools. | C6: Not-Executed
A7: 6 | B7: Verify that no loan-related notification is ever dispatched. | C7: Not-Executed
A8: 7 | B8: Verify that no loan record can be created through any surface. | C8: Not-Executed
A9: 8 | B9: Verify that no loan figure appears in any financial report or dashboard. | C9: Not-Executed

Sheet M19 Learning & Content
A1: S/N | B1: Test Scenario | C1: Status | D1: Comment | F1: CASPAA — Web / PWA · M19 Learning & Content
A2: 1 | B2: Verify that a teacher can create a lesson plan with title, subject, class and term. | C2: Not-Executed | F2: Total test scenarios | G2: Pass | H2: Fail | I2: Blocker | J2: Not-Executed
A3: 2 | B3: Verify that notes, files, links and video can be attached to content. | C3: Not-Executed | F3: =COUNTA(B2:B12) | G3: =COUNTIF(C2:C12,"Passed") | H3: =COUNTIF(C2:C12,"Failed") | I3: =COUNTIF(C2:C12,"Blocker") | J3: =COUNTIF(C2:C12,"Not-Executed")
A4: 3 | B4: Verify that unpublished draft content is hidden from students. | C4: Not-Executed
A5: 4 | B5: Verify that publishing makes content visible to the correct class only. | C5: Not-Executed
A6: 5 | B6: Verify that a student in another class cannot see the material. | C6: Not-Executed
A7: 6 | B7: Verify that content is scoped to the correct subject as well as the class. | C7: Not-Executed
A8: 7 | B8: Verify that attachments render or download correctly for students. | C8: Not-Executed
A9: 8 | B9: Verify that a large file upload is handled gracefully with progress feedback. | C9: Not-Executed
A10: 9 | B10: Verify that an unsupported file type is rejected with a clear message. | C10: Not-Executed
A11: 10 | B11: Verify that admin oversight shows all published materials school-wide. | C11: Not-Executed
A12: 11 | B12: Verify that deleted material disappears from the student learning area. | C12: Not-Executed

Sheet M20 Behaviour & Discipline
A1: S/N | B1: Test Scenario | C1: Status | D1: Comment | F1: CASPAA — Web / PWA · M20 Behaviour & Discipline
A2: 1 | B2: Verify that a behaviour incident can be recorded with category, note and action taken. | C2: Not-Executed | F2: Total test scenarios | G2: Pass | H2: Fail | I2: Blocker | J2: Not-Executed
A3: 2 | B3: Verify that a merit can be recorded and is distinguished from an incident. | C3: Not-Executed | F3: =COUNTA(B2:B13) | G3: =COUNTIF(C2:C13,"Passed") | H3: =COUNTIF(C2:C13,"Failed") | I3: =COUNTIF(C2:C13,"Blocker") | J3: =COUNTIF(C2:C13,"Not-Executed")
A4: 3 | B4: Verify that the record appears on the student profile with timestamp and author. | C4: Not-Executed
A5: 4 | B5: Verify that a sanction can be applied with a type, reason and date range. | C5: Not-Executed
A6: 5 | B6: Verify that a suspension reflects on the student's active status for its period. | C6: Not-Executed
A7: 6 | B7: Verify that a sanction with a duration auto-expires at its end date. | C7: Not-Executed
A8: 7 | B8: Verify that a suspension raised here appears in the Students suspensions register. | C8: Not-Executed
A9: 8 | B9: Verify that parents are notified for incidents above the agreed threshold. | C9: Not-Executed
A10: 9 | B10: Verify that a routine record below the threshold does not notify the parent. | C10: Not-Executed
A11: 10 | B11: Verify that a student can view their own behaviour record. | C11: Not-Executed
A12: 11 | B12: Verify that a parent can view their own child's behaviour record only. | C12: Not-Executed
A13: 12 | B13: Verify that behaviour records are auditable and attributed to their author. | C13: Not-Executed

Sheet M21 Messaging
A1: S/N | B1: Test Scenario | C1: Status | D1: Comment | F1: CASPAA — Web / PWA · M21 Messaging
A2: 1 | B2: Verify that a parent can start a direct message thread with their child's teacher. | C2: Not-Executed | F2: Total test scenarios | G2: Pass | H2: Fail | I2: Blocker | J2: Not-Executed
A3: 2 | B3: Verify that the teacher is notified of a new message. | C3: Not-Executed | F3: =COUNTA(B2:B12) | G3: =COUNTIF(C2:C12,"Passed") | H3: =COUNTIF(C2:C12,"Failed") | I3: =COUNTIF(C2:C12,"Blocker") | J3: =COUNTIF(C2:C12,"Not-Executed")
A4: 3 | B4: Verify that a teacher can reply and the parent is notified. | C4: Not-Executed
A5: 4 | B5: Verify that the conversation remains threaded and correctly ordered. | C5: Not-Executed
A6: 5 | B6: Verify that full history is preserved and searchable. | C6: Not-Executed
A7: 6 | B7: Verify that a parent can only message staff linked to their own child. | C7: Not-Executed
A8: 7 | B8: Verify that a parent cannot message a teacher unrelated to their child. | C8: Not-Executed
A9: 8 | B9: Verify that admin oversight shows all threads read-only. | C9: Not-Executed
A10: 9 | B10: Verify that the admin is never injected into a thread by viewing it. | C10: Not-Executed
A11: 10 | B11: Verify that messaging is distinct from the teacher-initiated diary. | C11: Not-Executed
A12: 11 | B12: Verify that a notification fires on each new message. | C12: Not-Executed

Sheet M22 Front Desk
A1: S/N | B1: Test Scenario | C1: Status | D1: Comment | F1: CASPAA — Web / PWA · M22 Front Desk
A2: 1 | B2: Verify that a tour request submitted on the public site requires no account. | C2: Not-Executed | F2: Total test scenarios | G2: Pass | H2: Fail | I2: Blocker | J2: Not-Executed
A3: 2 | B3: Verify that a tour request lands in Front Desk with a new-lead badge. | C3: Not-Executed | F3: =COUNTA(B2:B18) | G3: =COUNTIF(C2:C18,"Passed") | H3: =COUNTIF(C2:C18,"Failed") | I3: =COUNTIF(C2:C18,"Blocker") | J3: =COUNTIF(C2:C18,"Not-Executed")
A4: 3 | B4: Verify that the badge counts only unworked tours and career leads. | C4: Not-Executed
A5: 4 | B5: Verify that a tour can move from Requested to Confirmed with a date and time. | C5: Not-Executed
A6: 5 | B6: Verify that confirming a tour notifies the family with the date and time. | C6: Not-Executed
A7: 6 | B7: Verify that a tour can be marked Completed or Cancelled. | C7: Not-Executed
A8: 7 | B8: Verify that each status change is stamped with the actor and time. | C8: Not-Executed
A9: 8 | B9: Verify that a completed tour can be converted into an admission application. | C9: Not-Executed
A10: 9 | B10: Verify that conversion pre-fills the family's details with no re-keying. | C10: Not-Executed
A11: 10 | B11: Verify that the converted application links back to the originating tour. | C11: Not-Executed
A12: 11 | B12: Verify that a career enquiry captures the role interest and CV attachment. | C12: Not-Executed
A13: 12 | B13: Verify that a career lead can be shortlisted or declined. | C13: Not-Executed
A14: 13 | B14: Verify that a shortlisted candidate can be hired into Staff. | C14: Not-Executed
A15: 14 | B15: Verify that a lead submitted on one school's site never appears in another's Front Desk. | C15: Not-Executed
... A18: 17 | B18: Verify that an empty Front Desk shows a no-requests state rather than a blank table. | C18: Not-Executed

Sheet M23 Operations Hub
A1: S/N | B1: Test Scenario | C1: Status | D1: Comment | F1: CASPAA — Web / PWA · M23 Operations Hub
A2: 1 | B2: Verify that a visitor can be checked in with name, relation, host, purpose and vehicle. | C2: Not-Executed | F2: Total test scenarios | G2: Pass | H2: Fail | I2: Blocker | J2: Not-Executed
A3: 2 | B3: Verify that the To See picker lists only active staff of this school. | C3: Not-Executed | F3: =COUNTA(B2:B38) | G3: =COUNTIF(C2:C38,"Passed") | H3: =COUNTIF(C2:C38,"Failed") | I3: =COUNTIF(C2:C38,"Blocker") | J3: =COUNTIF(C2:C38,"Not-Executed")
A4: 3 | B4: Verify that a visitor check-in is stamped with the date and time. | C4: Not-Executed
A5: 4 | B5: Verify that the currently-on-premises count equals visitors with no check-out. | C5: Not-Executed
A6: 5 | B6: Verify that a visitor can be checked out in a single action from the row. | C6: Not-Executed
A7: 6 | B7: Verify that the today counter counts only check-ins dated today. | C7: Not-Executed
A8: 7 | B8: Verify that the visitor log is ordered with the newest check-in first. | C8: Not-Executed
A9: 8 | B9: Verify that a visitor entry cannot be edited or deleted after creation. | C9: Not-Executed
A10: 9 | B10: Verify that an un-checked-out visit from a prior day is flagged. | C10: Not-Executed
A11: 10 | B11: Verify that a book can be added to the library with a total copy count. | C11: Not-Executed
A12: 11 | B12: Verify that copies available equals total copies minus active loans. | C12: Not-Executed
A13: 12 | B13: Verify that issuing is blocked when no copy is available. | C13: Not-Executed
A14: 13 | B14: Verify that issuing a copy decrements availability and creates an active loan. | C14: Not-Executed
A15: 14 | B15: Verify that returning a copy increments availability and closes the loan. | C15: Not-Executed
... A38: 37 | B38: Verify that unenrolling a billed student raises a credit line rather than deleting the charge. | C38: Not-Executed

Sheet M24 School Store
A1: S/N | B1: Test Scenario | C1: Status | D1: Comment | F1: CASPAA — Web / PWA · M24 School Store
A2: 1 | B2: Verify that an item can be created with cost price, selling price, unit and stock. | C2: Not-Executed | F2: Total test scenarios | G2: Pass | H2: Fail | I2: Blocker | J2: Not-Executed
A3: 2 | B3: Verify that margin equals selling price minus cost price. | C3: Not-Executed | F3: =COUNTA(B2:B17) | G3: =COUNTIF(C2:C17,"Passed") | H3: =COUNTIF(C2:C17,"Failed") | I3: =COUNTIF(C2:C17,"Blocker") | J3: =COUNTIF(C2:C17,"Not-Executed")
A4: 3 | B4: Verify that margin percentage equals margin divided by selling price, rounded. | C4: Not-Executed
A5: 4 | B5: Verify that a zero selling price shows a margin of nil rather than a divide error. | C5: Not-Executed
A6: 5 | B6: Verify that margin banding is 30 percent or more good, 15 to 29 fair, below 15 warning. | C6: Not-Executed
A7: 6 | B7: Verify that margin banding is not communicated by colour alone. | C7: Not-Executed
A8: 7 | B8: Verify that a student purchase can be recorded with item and quantity. | C8: Not-Executed
A9: 8 | B9: Verify that the purchase posts to the student's ledger as its own dated charge. | C9: Not-Executed
A10: 9 | B10: Verify that units sold sums quantity rather than counting purchase records. | C10: Not-Executed
A11: 10 | B11: Verify that stock value is shown at cost price, not selling price. | C11: Not-Executed
A12: 11 | B12: Verify that a deactivated item disappears from the catalogue. | C12: Not-Executed
A13: 12 | B13: Verify that a deactivated item still appears on past purchases and statements. | C13: Not-Executed
A14: 13 | B14: Verify that cost price is never visible to a parent in any view, statement or receipt. | C14: Not-Executed
A15: 14 | B15: Verify that reversing a purchase raises a credit line rather than deleting the charge. | C15: Not-Executed
... A17: 16 | B17: Verify that store item changes and purchases write audit log entries. | C17: Not-Executed

Sheet M25 Settings & Branding
A1: S/N | B1: Test Scenario | C1: Status | D1: Comment | F1: CASPAA — Web / PWA · M25 Settings & Branding
A2: 1 | B2: Verify that a school logo can be uploaded and appears in the navigation. | C2: Not-Executed | F2: Total test scenarios | G2: Pass | H2: Fail | I2: Blocker | J2: Not-Executed
A3: 2 | B3: Verify that the logo appears on report cards, statements and receipts. | C3: Not-Executed | F3: =COUNTA(B2:B20) | G3: =COUNTIF(C2:C20,"Passed") | H3: =COUNTIF(C2:C20,"Failed") | I3: =COUNTIF(C2:C20,"Blocker") | J3: =COUNTIF(C2:C20,"Not-Executed")
A4: 3 | B4: Verify that an oversized or wrong-format logo is rejected with a clear message. | C4: Not-Executed
A5: 4 | B5: Verify that brand colours apply across the interface without a reload. | C5: Not-Executed
A6: 5 | B6: Verify that academic structure changes are reflected in the relevant modules. | C6: Not-Executed
A7: 6 | B7: Verify that term dates set here are the only source used by the calendar. | C7: Not-Executed
A8: 7 | B8: Verify that a new custom list entry is immediately selectable where it applies. | C8: Not-Executed
A9: 8 | B9: Verify that a custom role can be created with specific module permissions. | C9: Not-Executed
A10: 9 | B10: Verify that a user with a custom role sees exactly the permitted modules in the nav. | C10: Not-Executed
A11: 10 | B11: Verify that a custom role blocks deep links to unpermitted views. | C11: Not-Executed
A12: 11 | B12: Verify that payment gateway keys are masked after saving. | C12: Not-Executed
A13: 12 | B13: Verify that a gateway test connection reports the real success or error. | C13: Not-Executed
A14: 13 | B14: Verify that gateway secrets never appear in the audit log payload. | C14: Not-Executed
A15: 14 | B15: Verify that a data backup export produces a complete snapshot of this tenant only. | C15: Not-Executed
... A20: 19 | B20: Verify that a branch inherits or overrides group branding as configured. | C20: Not-Executed

Sheet M26 Reports & Analytics
A1: S/N | B1: Test Scenario | C1: Status | D1: Comment | F1: CASPAA — Web / PWA · M26 Reports & Analytics
A2: 1 | B2: Verify that the enrolment report headcount matches the active student count. | C2: Not-Executed | F2: Total test scenarios | G2: Pass | H2: Fail | I2: Blocker | J2: Not-Executed
A3: 2 | B3: Verify that the leavers report lists who left, when and why. | C3: Not-Executed | F3: =COUNTA(B2:B18) | G3: =COUNTIF(C2:C18,"Passed") | H3: =COUNTIF(C2:C18,"Failed") | I3: =COUNTIF(C2:C18,"Blocker") | J3: =COUNTIF(C2:C18,"Not-Executed")
A4: 3 | B4: Verify that the attendance report figures match the attendance module. | C4: Not-Executed
A5: 4 | B5: Verify that the financial report reconciles exactly to the ledger. | C5: Not-Executed
A6: 5 | B6: Verify that the applications report reflects the admissions funnel accurately. | C6: Not-Executed
A7: 6 | B7: Verify that the insights badge count matches the critical items on the Insights tab. | C7: Not-Executed
A8: 7 | B8: Verify that applying a filter changes the report shown on screen. | C8: Not-Executed
A9: 8 | B9: Verify that an export contains exactly the filtered set. | C9: Not-Executed
A10: 9 | B10: Verify that the export states the filters that were applied. | C10: Not-Executed
A11: 10 | B11: Verify that a P&L export opens correctly in a spreadsheet application. | C11: Not-Executed
A12: 11 | B12: Verify that the accounting journal export matches the target package format. | C12: Not-Executed
A13: 12 | B13: Verify that the print centre produces one document per student with branding. | C13: Not-Executed
A14: 13 | B14: Verify that every printed document carries a computer-generated footer. | C14: Not-Executed
A15: 14 | B15: Verify that a term with no data shows an empty state rather than a zeroed chart. | C15: Not-Executed
... A18: 17 | B18: Verify that a large export does not freeze the page. | C18: Not-Executed

Sheet M27 Audit Log
A1: S/N | B1: Test Scenario | C1: Status | D1: Comment | F1: CASPAA — Web / PWA · M27 Audit Log
A2: 1 | B2: Verify that a sensitive action writes exactly one audit entry. | C2: Not-Executed | F2: Total test scenarios | G2: Pass | H2: Fail | I2: Blocker | J2: Not-Executed
A3: 2 | B3: Verify that the entry records actor, action, target and timestamp. | C3: Not-Executed | F3: =COUNTA(B2:B16) | G3: =COUNTIF(C2:C16,"Passed") | H3: =COUNTIF(C2:C16,"Failed") | I3: =COUNTIF(C2:C16,"Blocker") | J3: =COUNTIF(C2:C16,"Not-Executed")
A4: 3 | B4: Verify that the acting user is named, not just their role. | C4: Not-Executed
A5: 4 | B5: Verify that no UI path allows editing an audit entry. | C5: Not-Executed
A6: 5 | B6: Verify that no UI path allows deleting an audit entry. | C6: Not-Executed
A7: 6 | B7: Verify that filtering by Students returns only student-category actions. | C7: Not-Executed
A8: 7 | B8: Verify that filtering by Finance returns only finance-category actions. | C8: Not-Executed
A9: 8 | B9: Verify that the All filter returns every entry including uncategorised actions. | C9: Not-Executed
A10: 9 | B10: Verify that the 7 day, 30 day, term and all date ranges filter correctly. | C10: Not-Executed
A11: 10 | B11: Verify that search matches actor and target names case-insensitively. | C11: Not-Executed
A12: 11 | B12: Verify that entries are ordered newest first consistently. | C12: Not-Executed
A13: 12 | B13: Verify that no entry contains a password, token or gateway key. | C13: Not-Executed
A14: 13 | B14: Verify that a failed audit write prevents the action from silently succeeding. | C14: Not-Executed
A15: 14 | B15: Verify that a group owner sees a branch's log only while switched into it. | C15: Not-Executed
A16: 15 | B16: Verify that an empty filter result shows a no-matching-activity state. | C16: Not-Executed

Sheet M28 Notifications
A1: S/N | B1: Test Scenario | C1: Status | D1: Comment | F1: CASPAA — Web / PWA · M28 Notifications
A2: 1 | B2: Verify that the school can select the default channels used for outbound notifications. | C2: Not-Executed | F2: Total test scenarios | G2: Pass | H2: Fail | I2: Blocker | J2: Not-Executed
A3: 2 | B3: Verify that the SMS channel is rendered disabled and cannot be switched on. | C3: Not-Executed | F3: =COUNTA(B2:B16) | G3: =COUNTIF(C2:C16,"Passed") | H3: =COUNTIF(C2:C16,"Failed") | I3: =COUNTIF(C2:C16,"Blocker") | J3: =COUNTIF(C2:C16,"Not-Executed")
A4: 3 | B4: Verify that the reason SMS is unavailable is stated on screen rather than left blank. | C4: Not-Executed
A5: 4 | B5: Verify that disabling a channel stops every module from using it. | C5: Not-Executed
A6: 5 | B6: Verify that switching a trigger off stops that notification on all channels. | C6: Not-Executed
A7: 6 | B7: Verify that the sickbay send-home alert fires even with every trigger switched off. | C7: Not-Executed
A8: 7 | B8: Verify that a parent receives notifications relating only to their own children. | C8: Not-Executed
A9: 8 | B9: Verify that an in-app notification is written even when an external channel fails. | C9: Not-Executed
A10: 9 | B10: Verify that the bell unread count matches the number of genuinely unread items. | C10: Not-Executed
A11: 10 | B11: Verify that opening a notification clears the unread state of that item only. | C11: Not-Executed
A12: 11 | B12: Verify that opening a notification deep-links to the relevant record. | C12: Not-Executed
A13: 12 | B13: Verify that a delivery failure is logged and never fails the originating action. | C13: Not-Executed
A14: 13 | B14: Verify that the same trigger for the same target on the same day sends only once. | C14: Not-Executed
A15: 14 | B15: Verify that notifications queued offline dispatch on reconnect without duplicating. | C15: Not-Executed
A16: 15 | B16: Verify that no notification body contains another family's data. | C16: Not-Executed

Sheet M29 Help & Support
A1: S/N | B1: Test Scenario | C1: Status | D1: Comment | F1: CASPAA — Web / PWA · M29 Help & Support
A2: 1 | B2: Verify that live chat opens with a greeting rather than a blank window. | C2: Not-Executed | F2: Total test scenarios | G2: Pass | H2: Fail | I2: Blocker | J2: Not-Executed
A3: 2 | B3: Verify that chat history survives navigation and a page reload. | C3: Not-Executed | F3: =COUNTA(B2:B16) | G3: =COUNTIF(C2:C16,"Passed") | H3: =COUNTIF(C2:C16,"Failed") | I3: =COUNTIF(C2:C16,"Blocker") | J3: =COUNTIF(C2:C16,"Not-Executed")
A4: 3 | B4: Verify that chat is scoped to the signed-in school only. | C4: Not-Executed
A5: 4 | B5: Verify that a ticket can be raised with a subject, category and message. | C5: Not-Executed
A6: 5 | B6: Verify that the open-ticket badge counts tickets not yet resolved. | C6: Not-Executed
A7: 6 | B7: Verify that an agent reply from the COP desk appears in the school's ticket thread. | C7: Not-Executed
A8: 7 | B8: Verify that the school is notified when an agent replies. | C8: Not-Executed
A9: 8 | B9: Verify that ticket status is identical in the school view and the COP queue. | C9: Not-Executed
A10: 9 | B10: Verify that the help centre is searchable by keyword. | C10: Not-Executed
A11: 10 | B11: Verify that a search with no results offers to raise a ticket. | C11: Not-Executed
A12: 11 | B12: Verify that a feature request raised from a locked screen appears in My Tickets. | C12: Not-Executed
A13: 12 | B13: Verify that Help and Support is reachable from the billing screen. | C13: Not-Executed
A14: 13 | B14: Verify that Help and Support is never hidden by entitlement gating. | C14: Not-Executed
A15: 14 | B15: Verify that a school cannot see another school's tickets or chat. | C15: Not-Executed
A16: 15 | B16: Verify that composing offline shows a will-send-on-reconnect state. | C16: Not-Executed

Sheet M30 Subscription & Billing
A1: S/N | B1: Test Scenario | C1: Status | D1: Comment | F1: CASPAA — Web / PWA · M30 Subscription & Billing
A2: 1 | B2: Verify that the owner can see their current plan, its price and the renewal date. | C2: Not-Executed | F2: Total test scenarios | G2: Pass | H2: Fail | I2: Blocker | J2: Not-Executed
A3: 2 | B3: Verify that the plan table shows what the current tier includes and what the tier above adds. | C3: Not-Executed | F3: =COUNTA(B2:B23) | G3: =COUNTIF(C2:C23,"Passed") | H3: =COUNTIF(C2:C23,"Failed") | I3: =COUNTIF(C2:C23,"Blocker") | J3: =COUNTIF(C2:C23,"Not-Executed")
A4: 3 | B4: Verify that an upgrade quotes a pro-rata amount for the days remaining in the period. | C4: Not-Executed
A5: 4 | B5: Verify that the pro-rata amount is proportional to days remaining, not the full month. | C5: Not-Executed
A6: 5 | B6: Verify that paying the upgrade invoice widens entitlements immediately with no re-login. | C6: Not-Executed
A7: 6 | B7: Verify that a zero-cost upgrade completes without a payment gateway trip. | C7: Not-Executed
A8: 7 | B8: Verify that a downgrade is scheduled for the renewal date and is not applied on the spot. | C8: Not-Executed
A9: 8 | B9: Verify that all current-tier features remain usable until the downgrade takes effect. | C9: Not-Executed
A10: 9 | B10: Verify that a downgrade never produces a refund or a credit balance. | C10: Not-Executed
A11: 10 | B11: Verify that the pending plan change and its effective date stay visible until it applies. | C11: Not-Executed
A12: 11 | B12: Verify that a scheduled change can be cancelled with no charge or credit side effect. | C12: Not-Executed
A13: 12 | B13: Verify that the downgrade warning lists only tier-derived features, excluding overrides. | C13: Not-Executed
A14: 13 | B14: Verify that auto-renew can be switched off and access continues to the end of the paid period. | C14: Not-Executed
A15: 14 | B15: Verify that a renewal due in 30 days or fewer shows an amber chip on the owner's dashboard. | C15: Not-Executed
... A23: 22 | B23: Verify that every plan change, payment and auto-renew toggle writes an audit log entry. | C23: Not-Executed

Sheet M31 AI Assistant & Insights
A1: S/N | B1: Test Scenario | C1: Status | D1: Comment | F1: CASPAA — Web / PWA · M31 AI Assistant & Insights
A2: 1 | B2: Verify that an overdue invoice with a balance raises a critical insight. | C2: Not-Executed | F2: Total test scenarios | G2: Pass | H2: Fail | I2: Blocker | J2: Not-Executed
A3: 2 | B3: Verify that a student absent three or more consecutive days raises a critical insight. | C3: Not-Executed | F3: =COUNTA(B2:B20) | G3: =COUNTIF(C2:C20,"Passed") | H3: =COUNTIF(C2:C20,"Failed") | I3: =COUNTIF(C2:C20,"Blocker") | J3: =COUNTIF(C2:C20,"Not-Executed")
A4: 3 | B4: Verify that fee collection below the configured target raises a warning insight. | C4: Not-Executed
A5: 4 | B5: Verify that an admissions visit past its scheduled date raises a warning insight. | C5: Not-Executed
A6: 5 | B6: Verify that an application pending seven or more days raises an info insight. | C6: Not-Executed
A7: 6 | B7: Verify that a club with one to four enrolments raises an info insight. | C7: Not-Executed
A8: 7 | B8: Verify that no rules firing produces an explicit all-clear item rather than an empty list. | C8: Not-Executed
A9: 8 | B9: Verify that insights are ordered critical, then warning, then info. | C9: Not-Executed
A10: 9 | B10: Verify that every insight links to the screen where it can be resolved. | C10: Not-Executed
A11: 10 | B11: Verify that insights state counts, amounts or names rather than vague text. | C11: Not-Executed
A12: 11 | B12: Verify that insights recompute live and are never served stale. | C12: Not-Executed
A13: 12 | B13: Verify that changing the collection target changes which insights fire. | C13: Not-Executed
A14: 13 | B14: Verify that changing the attendance threshold changes which students are flagged. | C14: Not-Executed
A15: 14 | B15: Verify that switching an AI feature off removes it everywhere it appeared. | C15: Not-Executed
... A20: 19 | B20: Verify that insight rules run without any student data leaving the tenant. | C20: Not-Executed

Sheet M32 Public Site & Acquisition
A1: S/N | B1: Test Scenario | C1: Status | D1: Comment | F1: CASPAA — Web / PWA · M32 Public Site & Acquisition
A2: 1 | B2: Verify that the public home page loads without an account. | C2: Not-Executed | F2: Total test scenarios | G2: Pass | H2: Fail | I2: Blocker | J2: Not-Executed
A3: 2 | B3: Verify that the pricing page matches the plan pricing used in Billing. | C3: Not-Executed | F3: =COUNTA(B2:B19) | G3: =COUNTIF(C2:C19,"Passed") | H3: =COUNTIF(C2:C19,"Failed") | I3: =COUNTIF(C2:C19,"Blocker") | J3: =COUNTIF(C2:C19,"Not-Executed")
A4: 3 | B4: Verify that a solutions page renders correctly for each role. | C4: Not-Executed
A5: 4 | B5: Verify that the contact form submits successfully. | C5: Not-Executed
A6: 5 | B6: Verify that a public route renders its page rather than the sign-in screen. | C6: Not-Executed
A7: 6 | B7: Verify that back navigation from a public route behaves correctly. | C7: Not-Executed
A8: 7 | B8: Verify that a tour booking submits without an account. | C8: Not-Executed
A9: 8 | B9: Verify that an admission application submits without an account. | C9: Not-Executed
A10: 9 | B10: Verify that a career enquiry submits with a CV attachment. | C10: Not-Executed
A11: 10 | B11: Verify that a proprietor can self-register a school. | C11: Not-Executed
A12: 11 | B12: Verify that a verification document can be uploaded during registration. | C12: Not-Executed
A13: 12 | B13: Verify that only accepted document file types are allowed. | C13: Not-Executed
A14: 13 | B14: Verify that an oversized document is rejected with a clear message. | C14: Not-Executed
A15: 14 | B15: Verify that the new school is created with a pending verification status. | C15: Not-Executed
... A19: 18 | B19: Verify that public pricing and plan features read from the same source as entitlements. | C19: Not-Executed

Sheet M33 Role Dashboards
A1: S/N | B1: Test Scenario | C1: Status | D1: Comment | F1: CASPAA — Web / PWA · M33 Role Dashboards
A2: 1 | B2: Verify that each role lands on the dashboard built for that role. | C2: Not-Executed | F2: Total test scenarios | G2: Pass | H2: Fail | I2: Blocker | J2: Not-Executed
A3: 2 | B3: Verify that a dashboard shows only what the role's permissions allow. | C3: Not-Executed | F3: =COUNTA(B2:B19) | G3: =COUNTIF(C2:C19,"Passed") | H3: =COUNTIF(C2:C19,"Failed") | I3: =COUNTIF(C2:C19,"Blocker") | J3: =COUNTIF(C2:C19,"Not-Executed")
A4: 3 | B4: Verify that every KPI figure matches its source module exactly. | C4: Not-Executed
A5: 4 | B5: Verify that an action chip appears only while its condition holds. | C5: Not-Executed
A6: 5 | B6: Verify that a chip disappears once its condition is resolved. | C6: Not-Executed
A7: 6 | B7: Verify that clicking a chip deep-links to the specific tab with the relevant filter. | C7: Not-Executed
A8: 7 | B8: Verify that a subscription renewal within seven days shows a red chip. | C8: Not-Executed
A9: 8 | B9: Verify that a subscription renewal within thirty days shows an amber chip. | C9: Not-Executed
A10: 9 | B10: Verify that chip severity is not conveyed by colour alone. | C10: Not-Executed
A11: 10 | B11: Verify that a low-stock chip count matches the inventory module. | C11: Not-Executed
A12: 11 | B12: Verify that an overdue-books chip count matches the library Overdue tab. | C12: Not-Executed
A13: 12 | B13: Verify that a new school with no data shows a guided get-started state. | C13: Not-Executed
A14: 13 | B14: Verify that a parent with several children sees each child distinctly. | C14: Not-Executed
A15: 14 | B15: Verify that no parent figure aggregates in a way that hides an outstanding debt. | C15: Not-Executed
... A19: 18 | B19: Verify that the dashboard degrades gracefully offline with a last-updated marker. | C19: Not-Executed

Sheet M34 COP Platform Settings
A1: S/N | B1: Test Scenario | C1: Status | D1: Comment | F1: CASPAA — Web / PWA · M34 COP Platform Settings
A2: 1 | B2: Verify that a global feature flag can be toggled from the COP. | C2: Not-Executed | F2: Total test scenarios | G2: Pass | H2: Fail | I2: Blocker | J2: Not-Executed
A3: 2 | B3: Verify that a flag switched off applies to every school without a redeploy. | C3: Not-Executed | F3: =COUNTA(B2:B14) | G3: =COUNTIF(C2:C14,"Passed") | H3: =COUNTIF(C2:C14,"Failed") | I3: =COUNTIF(C2:C14,"Blocker") | J3: =COUNTIF(C2:C14,"Not-Executed")
A4: 3 | B4: Verify that a global flag off overrides a per-school override that is on. | C4: Not-Executed
A5: 4 | B5: Verify that resolution order is global flag, then per-school override, then plan default. | C5: Not-Executed
A6: 5 | B6: Verify that beta capabilities carry a visible beta badge. | C6: Not-Executed
A7: 6 | B7: Verify that the lending flag off makes every loan entry point unreachable. | C7: Not-Executed
A8: 7 | B8: Verify that a school-side screen degrades to a locked state when a flag flips mid-session. | C8: Not-Executed
A9: 8 | B9: Verify that no school-side screen crashes when a flag flips mid-session. | C9: Not-Executed
A10: 9 | B10: Verify that security rows reflect the actual enforced configuration. | C10: Not-Executed
A11: 10 | B11: Verify that only COP roles with the platform-settings permission can open the screen. | C11: Not-Executed
A12: 11 | B12: Verify that turning off a capability in use requires explicit confirmation naming the impact. | C12: Not-Executed
A13: 12 | B13: Verify that every change records the actor, timestamp and previous value. | C13: Not-Executed
A14: 13 | B14: Verify that platform settings changes are written to an immutable log. | C14: Not-Executed

Sheet X1 Auth & Tenancy
A1: S/N | B1: Test Scenario | C1: Status | D1: Comment | F1: CASPAA — Web / PWA · X1 Auth & Tenancy
A2: 1 | B2: Verify that a user can sign in at the unified login and lands in the portal built for their role. | C2: Not-Executed | F2: Total test scenarios | G2: Pass | H2: Fail | I2: Blocker | J2: Not-Executed
A3: 2 | B3: Verify that invalid credentials show a clear error without revealing whether the email exists. | C3: Not-Executed | F3: =COUNTA(B2:B18) | G3: =COUNTIF(C2:C18,"Passed") | H3: =COUNTIF(C2:C18,"Failed") | I3: =COUNTIF(C2:C18,"Blocker") | J3: =COUNTIF(C2:C18,"Not-Executed")
A4: 3 | B4: Verify that a school owner signing in lands on the admin dashboard with the full navigation. | C4: Not-Executed
A5: 4 | B5: Verify that a parent signing in can see only their own children's data. | C5: Not-Executed
A6: 5 | B6: Verify that a teacher cannot reach any finance view via a direct URL or deep link. | C6: Not-Executed
A7: 6 | B7: Verify that data belonging to one school is never visible to a user of another school. | C7: Not-Executed
A8: 7 | B8: Verify that a self-registered proprietor is held at the verification gate. | C8: Not-Executed
A9: 8 | B9: Verify that the verification screen shows school name, official email and documents submitted. | C9: Not-Executed
A10: 9 | B10: Verify that a rejected proprietor sees the reviewer's reason verbatim and can re-submit. | C10: Not-Executed
A11: 10 | B11: Verify that approving a school lifts the gate without requiring a new sign-in. | C11: Not-Executed
A12: 11 | B12: Verify that a suspended school's users are blocked from signing in immediately. | C12: Not-Executed
A13: 12 | B13: Verify that Sign out is always reachable from the verification gate. | C13: Not-Executed
A14: 13 | B14: Verify that the session times out after the configured idle period. | C14: Not-Executed
A15: 14 | B15: Verify that deep-linking to a view the role lacks shows a denied screen, not a crash. | C15: Not-Executed
... A18: 17 | B18: Verify that MFA is enforced for admin roles where configured. | C18: Not-Executed

Sheet X2 Offline & PWA
A1: S/N | B1: Test Scenario | C1: Status | D1: Comment | F1: CASPAA — Web / PWA · X2 Offline & PWA
A2: 1 | B2: Verify that the app can be installed to the device home screen from the browser. | C2: Not-Executed | F2: Total test scenarios | G2: Pass | H2: Fail | I2: Blocker | J2: Not-Executed
A3: 2 | B3: Verify that the installed app launches with the school's own branding and icon. | C3: Not-Executed | F3: =COUNTA(B2:B14) | G3: =COUNTIF(C2:C14,"Passed") | H3: =COUNTIF(C2:C14,"Failed") | I3: =COUNTIF(C2:C14,"Blocker") | J3: =COUNTIF(C2:C14,"Not-Executed")
A4: 3 | B4: Verify that the app loads and renders while the device is fully offline. | C4: Not-Executed
A5: 4 | B5: Verify that a clear offline indicator is shown as soon as connectivity is lost. | C5: Not-Executed
A6: 5 | B6: Verify that attendance can be marked while offline. | C6: Not-Executed
A7: 6 | B7: Verify that offline changes sync automatically once connectivity returns. | C7: Not-Executed
A8: 7 | B8: Verify that no data is lost when the app is closed with offline changes pending. | C8: Not-Executed
A9: 8 | B9: Verify that a sync conflict resolves by the documented rule and is recorded in the audit log. | C9: Not-Executed
A10: 9 | B10: Verify that payment records survive an offline to online transition with zero loss. | C10: Not-Executed
A11: 10 | B11: Verify that the dashboard shows last-known figures with an offline last-updated marker. | C11: Not-Executed
A12: 11 | B12: Verify that actions requiring connectivity are disabled with an explanation while offline. | C12: Not-Executed
A13: 12 | B13: Verify that a service worker update does not discard unsynced local data. | C13: Not-Executed
A14: 13 | B14: Verify that the app recovers correctly after connectivity drops mid-submission. | C14: Not-Executed

Sheet X3 Usability & Accessibility
A1: S/N | B1: Test Scenario | C1: Status | D1: Comment | F1: CASPAA — Web / PWA · X3 Usability & Accessibility
A2: 1 | B2: Verify that users can navigate between screens and modules without confusion. | C2: Not-Executed | F2: Total test scenarios | G2: Pass | H2: Fail | I2: Blocker | J2: Not-Executed
A3: 2 | B3: Check for consistent design elements like fonts, colours and button styles throughout the app. | C3: Not-Executed | F3: =COUNTA(B2:B23) | G3: =COUNTIF(C2:C23,"Passed") | H3: =COUNTIF(C2:C23,"Failed") | I3: =COUNTIF(C2:C23,"Blocker") | J3: =COUNTIF(C2:C23,"Not-Executed")
A4: 3 | B4: Ensure that the placement of buttons, icons and menus feels natural and intuitive. | C4: Not-Executed
A5: 4 | B5: Verify that error messages are clear, helpful and guide the user to resolve the issue. | C5: Not-Executed
A6: 5 | B6: Ensure text and background colours meet WCAG AA contrast standards. | C6: Not-Executed
A7: 6 | B7: Verify that status is never communicated by colour alone. | C7: Not-Executed
A8: 7 | B8: Verify that font sizes adjust correctly when the user changes device text size settings. | C8: Not-Executed
A9: 8 | B9: Verify that every form input has an associated visible label. | C9: Not-Executed
A10: 9 | B10: Verify that the interface is fully operable by keyboard alone. | C10: Not-Executed
A11: 10 | B11: Verify that users can easily access help and support when needed. | C11: Not-Executed
A12: 11 | B12: Test the ease of creating, logging into and managing user accounts. | C12: Not-Executed
A13: 12 | B13: Verify that touch inputs, swipes and gestures are responsive and smooth. | C13: Not-Executed
A14: 13 | B14: Verify that users receive immediate feedback for actions like button presses or submissions. | C14: Not-Executed
A15: 14 | B15: Ensure loading spinners or progress bars appear during data loading or processing. | C15: Not-Executed
... A23: 22 | B23: Verify that no console errors are produced during a full navigation pass. | C23: Not-Executed

Sheet Test Cases (Detailed)
A1: Test Case ID | B1: Module | C1: Title / Objective | D1: Priority | E1: Type | F1: Preconditions | G1: Test Steps | H1: Test Data | I1: Expected Result | J1: Actual Result | K1: Status | L1: Comment
A2: TC_AUTH_001 | B2: X1 Auth | C2: Role-aware login routes each user to the correct portal | D2: High | E2: Functional | F2: A school is Active. Owner, teacher and parent accounts exist for it. | G2: 1. Open the school's CASPAA URL. 2. Sign in as the owner. 3. Note the landing view and nav. 4. Sign out. 5. Repeat as the teacher, then the parent. | H2: owner@school.test / teacher@school.test / parent@school.test | I2: Owner lands on the admin dashboard with full nav. Teacher lands on the teacher dashboard with no finance nav. Parent lands on the parent dashboard showing only their own children. | K2: Not-Executed
A3: TC_AUTH_002 | B3: X1 Auth | C3: Cross-tenant data isolation is enforced | D3: High | E3: Security | F3: Two schools, A and B, each with students. | G3: 1. Sign in as the School A admin. 2. Obtain a School B student record ID. 3. Deep-link to the student detail view with School B's ID. 4. Observe the response. | H3: School A admin; School B student ID stu_b_0001 | I3: The record is not returned. An access-denied or not-found screen renders. No School B data appears and the attempt is audited. | K3: Not-Executed
A4: TC_AUTH_003 | B4: X1 Auth | C4: Verification gate blocks an unverified proprietor | D4: High | E4: Negative | F4: A proprietor has self-registered; verification status is pending. | G4: 1. Sign in as the pending proprietor. 2. Observe the landing screen. 3. Deep-link to the admin dashboard URL. 4. Deep-link to the finance view. | H4: pending.proprietor@school.test | I4: The verification screen renders every time. School name, official email and documents are shown. No module is reachable by deep link. Sign out remains available. | K4: Not-Executed
A5: TC_STU_001 | B5: M01 Students | C5: Duplicate admission number is rejected | D5: High | E5: Negative | F5: A student already exists with admission number ADM/2026/001. | G5: 1. Sign in as admin. 2. Students > Add Student. 3. Complete all required fields. 4. Enter admission number ADM/2026/001. 5. Save. | H5: Name Test Child; Class JSS1A; Adm no ADM/2026/001 | I5: A validation error states the admission number is in use. The student is not created and no partial record is written. | K5: Not-Executed
A6: TC_STU_002 | B6: M01 Students | C6: New student propagates to roster, attendance and fees | D6: High | E6: Functional | F6: Class JSS1A exists with an active fee structure for the term. | G6: 1. Add a student to JSS1A with a linked parent and save. 2. Open the JSS1A roster. 3. Open Attendance for JSS1A. 4. Open Finance > Invoices filtered to JSS1A. 5. Sign in as the linked parent. | H6: Name Ada Obi; Class JSS1A; Parent parent@school.test | I6: The student appears in roster, attendance and fees immediately. The parent receives an in-app notification and sees the child on their dashboard. | K6: Not-Executed
A7: TC_STU_003 | B7: M01 Students | C7: Bulk CSV import is transactional per row | D7: Medium | E7: Functional | F7: A CSV of 10 students where rows 4 and 7 are invalid. | G7: 1. Students > Bulk Import CSV. 2. Upload the CSV. 3. Review the preview. 4. Confirm the import. 5. Check the student list. | H7: students_10rows.csv (rows 4, 7 invalid) | I7: Preview flags rows 4 and 7 with a specific reason each. On confirm 8 students import and 2 are reported skipped. Valid rows are unaffected. | K7: Not-Executed
A8: TC_ACA_001 | B8: M02 Academic | C8: Timetable clash for one teacher is surfaced | D8: Medium | E8: Negative | F8: Two classes exist and one teacher is assigned to both. | G8: 1. Academic > Timetable. 2. Assign the teacher to JSS1A period 3 Monday. 3. Assign the same teacher to JSS2A period 3 Monday. 4. Save and observe. | H8: Teacher Mr Okoro; Monday period 3 | I8: The clash is surfaced before or on save, naming the teacher, day and period. The conflicting assignment is not silently accepted. | K8: Not-Executed
A9: TC_ATT_001 | B9: M03 Attendance | C9: Absence triggers a same-day parent alert | D9: High | E9: Functional | F9: Teacher assigned to JSS1A; at least one student has a linked parent; absence trigger on. | G9: 1. Sign in as the class teacher. 2. Attendance > JSS1A. 3. Toggle one student to Absent. 4. Submit. 5. Sign in as that parent and open notifications. | H9: Class JSS1A; Student Ada Obi | I9: The register saves. The absent student's parent is alerted the same day naming child and date. Parents of present students receive nothing. | K9: Not-Executed
A10: TC_ATT_002 | B10: M03 Attendance | C10: Offline attendance syncs without duplicating | D10: High | E10: Functional | F10: PWA installed; teacher signed in and assigned to JSS1A. | G10: 1. Enable airplane mode. 2. Open Attendance for JSS1A. 3. Mark two students Absent and submit. 4. Confirm the queued offline state. 5. Restore connectivity. 6. Wait for sync and reload. | H10: Class JSS1A; today's date | I10: Submission queues offline and syncs on reconnect. Exactly one record exists for that class and date, both absences intact, parent alerts sent once. | K10: Not-Executed
A11: TC_RES_001 | B11: M04 Results | C11: Unapproved results are invisible to parents and students | D11: High | E11: Security | F11: A teacher has submitted but not had approved JSS1A Mathematics results. | G11: 1. Enter and submit JSS1A Mathematics results as the teacher. 2. Sign in as a JSS1A parent and open Results. 3. Sign in as a JSS1A student and open My Results. 4. Deep-link to the result record ID as the parent. | H11: Class JSS1A; Subject Mathematics; CA 28, Exam 55 | I11: Neither parent nor student sees any score. An amber pending banner shows instead. The deep link returns no result data. | K11: Not-Executed
A12: TC_RES_002 | B12: M04 Results | C12: Approval requires a comment for every student | D12: High | E12: Negative | F12: JSS1A Mathematics results pending; 20 students, 19 have comments. | G12: 1. Sign in as admin. 2. Open the pending JSS1A Mathematics broadsheet. 3. Leave one student without a comment. 4. Attempt Approve. 5. Add the missing comment. 6. Approve. | H12: Class JSS1A, 20 students | I12: Approve is disabled while a comment is missing, with the reason shown. Once complete, Approve succeeds and parents and students are notified exactly once. | K12: Not-Executed
A13: TC_RES_003 | B13: M04 Results | C13: Tied averages share a rank and the next rank skips | D13: Medium | E13: Functional | F13: Results entered where two students share an identical average. | G13: 1. Enter results producing averages 82, 78, 78, 71. 2. Submit and approve. 3. Open the broadsheet. 4. Open both tied students' report cards. | H13: Averages 82, 78, 78, 71 | I13: Ranks read 1, 2, 2, 4. Both tied students show rank 2 and rank 3 is skipped. Report cards match the broadsheet. | K13: Not-Executed
... A59: TC_USA_002 | B59: X3 Usability | C59: Status is never conveyed by colour alone | D59: Medium | E59: Accessibility | F59: Records exist in Passed, Failed, Overdue, Paid and Pending states across modules. | G59: 1. Open Invoices, Results, Attendance and the Library overdue tab. 2. Inspect each status indicator. 3. Re-inspect under a greyscale or colour-blindness simulation. 4. Check text and background contrast. | H59: Greyscale / deuteranopia simulation | I59: Every status carries a text label or icon alongside colour. All states stay distinguishable in greyscale and contrast meets WCAG AA. | K59: Not-Executed
