Workbook

Sheet Summary
A1: CASPAA — School Operating System · Test Execution Summary
A3: Test Area | B3: Total | C3: Passed | D3: Failed | E3: Blocker | F3: Not-Executed | G3: % Executed
A4: Auth & Tenancy | B4: ='Auth & Tenancy'!F3 | C4: ='Auth & Tenancy'!G3 | D4: ='Auth & Tenancy'!H3 | E4: ='Auth & Tenancy'!I3 | F4: ='Auth & Tenancy'!J3 | G4: =IF(B4=0,0,(B4-F4)/B4)
A5: Students & Admissions | B5: ='Students & Admissions'!F3 | C5: ='Students & Admissions'!G3 | D5: ='Students & Admissions'!H3 | E5: ='Students & Admissions'!I3 | F5: ='Students & Admissions'!J3 | G5: =IF(B5=0,0,(B5-F5)/B5)
A6: Attendance | B6: ='Attendance'!F3 | C6: ='Attendance'!G3 | D6: ='Attendance'!H3 | E6: ='Attendance'!I3 | F6: ='Attendance'!J3 | G6: =IF(B6=0,0,(B6-F6)/B6)
A7: Results & Reporting | B7: ='Results & Reporting'!F3 | C7: ='Results & Reporting'!G3 | D7: ='Results & Reporting'!H3 | E7: ='Results & Reporting'!I3 | F7: ='Results & Reporting'!J3 | G7: =IF(B7=0,0,(B7-F7)/B7)
A8: Finance & Fees (Ledger) | B8: ='Finance & Fees (Ledger)'!F3 | C8: ='Finance & Fees (Ledger)'!G3 | D8: ='Finance & Fees (Ledger)'!H3 | E8: ='Finance & Fees (Ledger)'!I3 | F8: ='Finance & Fees (Ledger)'!J3 | G8: =IF(B8=0,0,(B8-F8)/B8)
A9: Payments | B9: ='Payments'!F3 | C9: ='Payments'!G3 | D9: ='Payments'!H3 | E9: ='Payments'!I3 | F9: ='Payments'!J3 | G9: =IF(B9=0,0,(B9-F9)/B9)
A10: Subscription & Billing | B10: ='Subscription & Billing'!F3 | C10: ='Subscription & Billing'!G3 | D10: ='Subscription & Billing'!H3 | E10: ='Subscription & Billing'!I3 | F10: ='Subscription & Billing'!J3 | G10: =IF(B10=0,0,(B10-F10)/B10)
A11: Multi-branch & Entitlements | B11: ='Multi-branch & Entitlements'!F3 | C11: ='Multi-branch & Entitlements'!G3 | D11: ='Multi-branch & Entitlements'!H3 | E11: ='Multi-branch & Entitlements'!I3 | F11: ='Multi-branch & Entitlements'!J3 | G11: =IF(B11=0,0,(B11-F11)/B11)
A12: Notifications | B12: ='Notifications'!F3 | C12: ='Notifications'!G3 | D12: ='Notifications'!H3 | E12: ='Notifications'!I3 | F12: ='Notifications'!J3 | G12: =IF(B12=0,0,(B12-F12)/B12)
A13: Offline & PWA | B13: ='Offline & PWA'!F3 | C13: ='Offline & PWA'!G3 | D13: ='Offline & PWA'!H3 | E13: ='Offline & PWA'!I3 | F13: ='Offline & PWA'!J3 | G13: =IF(B13=0,0,(B13-F13)/B13)
A14: Usability | B14: ='Usability'!F3 | C14: ='Usability'!G3 | D14: ='Usability'!H3 | E14: ='Usability'!I3 | F14: ='Usability'!J3 | G14: =IF(B14=0,0,(B14-F14)/B14)
A15: TOTAL | B15: =SUM(B4:B14) | C15: =SUM(C4:C14) | D15: =SUM(D4:D14) | E15: =SUM(E4:E14) | F15: =SUM(F4:F14) | G15: =IF(B15=0,0,(B15-F15)/B15)
A18: Status legend
A19: Not-Executed | B19: Written but not yet run in this cycle.
A20: Passed | B20: Actual result matched the expected result.
A21: Failed | B21: Actual result differed. Log a defect and reference it in Comment.
A22: Blocker | B22: Could not be executed — a defect or missing data blocks the path.
A23: N/A | B23: Not applicable to this build, plan tier or platform.
A26: How to use this workbook
A27: 1. Upload to Google Drive and open with Google Sheets — tabs, dropdowns and colour rules are preserved.
A28: 2. Work one tab at a time. Set Status from the dropdown in column C; the counters in F3:J3 update live.
A29: 3. Record a defect ID and a one-line observation in Comment for every Failed or Blocker.
A30: 4. The Summary tab above rolls up every scenario tab automatically — do not overwrite its formulas.
A31: 5. 'Test Cases (Detailed)' holds step-level cases for the highest-risk flows; scenario tabs stay one-line.
A32: 6. Re-baseline by setting every Status back to Not-Executed at the start of each regression cycle.

Sheet Auth & Tenancy
A1: S/N | B1: Test Scenario | C1: Status | D1: Comment | F1: CASPAA — Web / PWA
A2: 1 | B2: Verify that a user can sign in at the unified login and lands in the portal built for their role. | C2: Not-Executed | F2: Total test scenarios | G2: Pass | H2: Fail | I2: Blocker | J2: Not-Executed
A3: 2 | B3: Verify that invalid credentials show a clear error without revealing whether the email exists. | C3: Not-Executed | F3: =COUNTA(B2:B18) | G3: =COUNTIF(C2:C18,"Passed") | H3: =COUNTIF(C2:C18,"Failed") | I3: =COUNTIF(C2:C18,"Blocker") | J3: =COUNTIF(C2:C18,"Not-Executed")
A4: 3 | B4: Verify that a school owner signing in lands on the admin dashboard with the full module navigation. | C4: Not-Executed
A5: 4 | B5: Verify that a parent signing in can see only their own children's data. | C5: Not-Executed
A6: 5 | B6: Verify that a teacher cannot reach any finance view via a direct URL or deep link. | C6: Not-Executed
A7: 6 | B7: Verify that data belonging to one school is never visible to a user of another school. | C7: Not-Executed
A8: 7 | B8: Verify that a self-registered proprietor is held at the verification gate and reaches no dashboard view. | C8: Not-Executed
A9: 8 | B9: Verify that the verification screen shows school name, official email and the documents submitted. | C9: Not-Executed
A10: 9 | B10: Verify that a rejected proprietor sees the reviewer's reason verbatim and can re-submit a document. | C10: Not-Executed
A11: 10 | B11: Verify that approving a school in the COP lifts the gate without requiring the proprietor to sign in again. | C11: Not-Executed
A12: 11 | B12: Verify that a suspended school's users are blocked from signing in immediately. | C12: Not-Executed
A13: 12 | B13: Verify that Sign out is always reachable from the verification gate. | C13: Not-Executed
A14: 13 | B14: Verify that the session times out and logs the user out after the configured idle period. | C14: Not-Executed
A15: 14 | B15: Verify that deep-linking to a view the role lacks shows a denied screen, not a blank page or a crash. | C15: Not-Executed
... A18: 17 | B18: Verify that a password reset link expires after use and cannot be replayed. | C18: Not-Executed

Sheet Students & Admissions
A1: S/N | B1: Test Scenario | C1: Status | D1: Comment | F1: CASPAA — Web / PWA
A2: 1 | B2: Verify that a student can be added with name, DOB, gender, class, house, admission number, photo and parent link. | C2: Not-Executed | F2: Total test scenarios | G2: Pass | H2: Fail | I2: Blocker | J2: Not-Executed
A3: 2 | B3: Verify that a duplicate admission number is rejected with a clear error and the student is not saved. | C3: Not-Executed | F3: =COUNTA(B2:B20) | G3: =COUNTIF(C2:C20,"Passed") | H3: =COUNTIF(C2:C20,"Failed") | I3: =COUNTIF(C2:C20,"Blocker") | J3: =COUNTIF(C2:C20,"Not-Executed")
A4: 3 | B4: Verify that a newly added student appears immediately in the class roster, attendance register and fee module. | C4: Not-Executed
A5: 4 | B5: Verify that the linked parent receives an in-app notification when their child is registered. | C5: Not-Executed
A6: 5 | B6: Verify that a CSV bulk import previews the parsed rows before anything is committed. | C6: Not-Executed
A7: 6 | B7: Verify that invalid CSV rows are flagged with a reason while the valid rows still import. | C7: Not-Executed
A8: 7 | B8: Verify that one bad row in a CSV never blocks the import of the remaining rows. | C8: Not-Executed
A9: 8 | B9: Verify that an online admission application can be accepted and converts into an enrolled student. | C9: Not-Executed
A10: 9 | B10: Verify that an admission application can be rejected with a reason recorded. | C10: Not-Executed
A11: 10 | B11: Verify that the Returning Student flow restores the prior record instead of creating a duplicate. | C11: Not-Executed
A12: 11 | B12: Verify that bulk promotion moves an entire class to the next class in one action. | C12: Not-Executed
A13: 12 | B13: Verify that graduating a class sets status to alumni and removes them from active rosters. | C13: Not-Executed
A14: 13 | B14: Verify that a graduated student's ledger and academic history remain fully intact. | C14: Not-Executed
A15: 14 | B15: Verify that deactivating a student hides them from active rosters but preserves their records. | C15: Not-Executed
... A20: 19 | B20: Verify that a student created in one branch is not visible in any other branch. | C20: Not-Executed

Sheet Attendance
A1: S/N | B1: Test Scenario | C1: Status | D1: Comment | F1: CASPAA — Web / PWA
A2: 1 | B2: Verify that a teacher can open their class and every student defaults to Present. | C2: Not-Executed | F2: Total test scenarios | G2: Pass | H2: Fail | I2: Blocker | J2: Not-Executed
A3: 2 | B3: Verify that today's date is auto-filled on the attendance screen. | C3: Not-Executed | F3: =COUNTA(B2:B17) | G3: =COUNTIF(C2:C17,"Passed") | H3: =COUNTIF(C2:C17,"Failed") | I3: =COUNTIF(C2:C17,"Blocker") | J3: =COUNTIF(C2:C17,"Not-Executed")
A4: 3 | B4: Verify that a student can be toggled between Present, Absent and Late. | C4: Not-Executed
A5: 4 | B5: Verify that a Late mark is recorded and reported distinctly from Absent. | C5: Not-Executed
A6: 5 | B6: Verify that submitting attendance saves it against schoolId, classId, date and teacher. | C6: Not-Executed
A7: 6 | B7: Verify that the same class and date cannot be submitted twice without an admin override. | C7: Not-Executed
A8: 7 | B8: Verify that parents of absent students receive an alert the same day. | C8: Not-Executed
A9: 8 | B9: Verify that the attendance percentage per class and per day is calculated correctly. | C9: Not-Executed
A10: 9 | B10: Verify that a parent can see only their own child's attendance record. | C10: Not-Executed
A11: 10 | B11: Verify that attendance marked while offline is stored locally and syncs on reconnect. | C11: Not-Executed
A12: 11 | B12: Verify that an offline submission which later syncs does not create a duplicate record. | C12: Not-Executed
A13: 12 | B13: Verify that a teacher can take attendance only for classes assigned to them. | C13: Not-Executed
A14: 13 | B14: Verify that an admin can view school-wide and per-class attendance rates. | C14: Not-Executed
A15: 14 | B15: Verify that a class with no students shows an empty state rather than an error. | C15: Not-Executed
... A17: 16 | B17: Verify that a student absent three consecutive days raises the at-risk insight. | C17: Not-Executed

Sheet Results & Reporting
A1: S/N | B1: Test Scenario | C1: Status | D1: Comment | F1: CASPAA — Web / PWA
A2: 1 | B2: Verify that a teacher can enter CA and exam scores for every student in a subject. | C2: Not-Executed | F2: Total test scenarios | G2: Pass | H2: Fail | I2: Blocker | J2: Not-Executed
A3: 2 | B3: Verify that the total is auto-computed as CA + Exam. | C3: Not-Executed | F3: =COUNTA(B2:B18) | G3: =COUNTIF(C2:C18,"Passed") | H3: =COUNTIF(C2:C18,"Failed") | I3: =COUNTIF(C2:C18,"Blocker") | J3: =COUNTIF(C2:C18,"Not-Executed")
A4: 3 | B4: Verify that the grade assigned matches the configured grade boundaries. | C4: Not-Executed
A5: 4 | B5: Verify that a score above the configured maximum is rejected. | C5: Not-Executed
A6: 5 | B6: Verify that a negative or non-numeric score is rejected. | C6: Not-Executed
A7: 6 | B7: Verify that submitting results marks them pending approval and not yet visible downstream. | C7: Not-Executed
A8: 7 | B8: Verify that pending results are not visible to parents or students in any view. | C8: Not-Executed
A9: 8 | B9: Verify that a parent or student sees a pending banner while results await approval. | C9: Not-Executed
A10: 9 | B10: Verify that Approve is disabled while any student is missing the required comment. | C10: Not-Executed
A11: 10 | B11: Verify that approving results notifies parents and students exactly once. | C11: Not-Executed
A12: 11 | B12: Verify that the broadsheet is ranked by average score. | C12: Not-Executed
A13: 12 | B13: Verify that tied averages share a rank and the next rank skips accordingly. | C13: Not-Executed
A14: 13 | B14: Verify that an approved report card can be printed with the school's branding. | C14: Not-Executed
A15: 14 | B15: Verify that printed report card figures match the broadsheet exactly. | C15: Not-Executed
... A18: 17 | B18: Verify that changing grade boundaries does not silently rewrite already-approved results. | C18: Not-Executed

Sheet Finance & Fees (Ledger)
A1: S/N | B1: Test Scenario | C1: Status | D1: Comment | F1: CASPAA — Web / PWA
A2: 1 | B2: Verify that a fee structure can be set per class and per term. | C2: Not-Executed | F2: Total test scenarios | G2: Pass | H2: Fail | I2: Blocker | J2: Not-Executed
A3: 2 | B3: Verify that bulk invoice generation creates exactly one invoice per active student. | C3: Not-Executed | F3: =COUNTA(B2:B23) | G3: =COUNTIF(C2:C23,"Passed") | H3: =COUNTIF(C2:C23,"Failed") | I3: =COUNTIF(C2:C23,"Blocker") | J3: =COUNTIF(C2:C23,"Not-Executed")
A4: 3 | B4: Verify that the generated invoice count matches the number of active students. | C4: Not-Executed
A5: 4 | B5: Verify that parents are notified once invoices are generated. | C5: Not-Executed
A6: 5 | B6: Verify that the student ledger shows each charge, discount and payment as its own dated row. | C6: Not-Executed
A7: 6 | B7: Verify that no charges, discounts or payments are lumped into a single combined line. | C7: Not-Executed
A8: 7 | B8: Verify that the opening balance is carried forward as its own labelled row. | C8: Not-Executed
A9: 8 | B9: Verify that the running balance is correct after every transaction on the ledger. | C9: Not-Executed
A10: 9 | B10: Verify that the invariant debit total minus credit total equals the balance holds for every student. | C10: Not-Executed
A11: 10 | B11: Verify that an overpayment is shown as a credit balance labelled Cr. | C11: Not-Executed
A12: 11 | B12: Verify that credit is auto-applied to the next invoice and the parent is notified. | C12: Not-Executed
A13: 12 | B13: Verify that sibling, bus and special discounts each appear as separate credit lines. | C13: Not-Executed
A14: 13 | B14: Verify that adding a line item to a bill recomputes total, balance and status. | C14: Not-Executed
A15: 14 | B15: Verify that removing a line item recomputes total, balance and status. | C15: Not-Executed
... A23: 22 | B23: Verify that every money action writes an immutable audit log entry. | C23: Not-Executed

Sheet Payments
A1: S/N | B1: Test Scenario | C1: Status | D1: Comment | F1: CASPAA — Web / PWA
A2: 1 | B2: Verify that a parent can pay an invoice by card. | C2: Not-Executed | F2: Total test scenarios | G2: Pass | H2: Fail | I2: Blocker | J2: Not-Executed
A3: 2 | B3: Verify that a parent can pay an invoice by bank transfer. | C3: Not-Executed | F3: =COUNTA(B2:B16) | G3: =COUNTIF(C2:C16,"Passed") | H3: =COUNTIF(C2:C16,"Failed") | I3: =COUNTIF(C2:C16,"Blocker") | J3: =COUNTIF(C2:C16,"Not-Executed")
A4: 3 | B4: Verify that a parent can pay an invoice by USSD. | C4: Not-Executed
A5: 4 | B5: Verify that a successful payment marks the invoice Paid and clears the balance. | C5: Not-Executed
A6: 5 | B6: Verify that a partial payment leaves the correct remaining balance and a part-paid status. | C6: Not-Executed
A7: 6 | B7: Verify that a receipt is available in the parent portal immediately after payment. | C7: Not-Executed
A8: 7 | B8: Verify that a receipt can be viewed, printed or downloaded at any time afterwards. | C8: Not-Executed
A9: 8 | B9: Verify that a failed payment is logged with its reason and is visible to finance. | C9: Not-Executed
A10: 9 | B10: Verify that a double-submitted payment never charges or credits twice. | C10: Not-Executed
A11: 10 | B11: Verify that a payment attempted offline queues and does not duplicate on reconnect. | C11: Not-Executed
A12: 11 | B12: Verify that multi-child Pay All processes each invoice in sequence with a method per child. | C12: Not-Executed
A13: 12 | B13: Verify that every payment is persisted with a unique gateway reference. | C13: Not-Executed
A14: 13 | B14: Verify that a parent cannot pay another family's invoice by altering the invoice ID. | C14: Not-Executed
A15: 14 | B15: Verify that the finance payments list reflects a new transaction immediately. | C15: Not-Executed
A16: 15 | B16: Verify that a payment gateway timeout leaves the invoice unpaid rather than in a partial state. | C16: Not-Executed

Sheet Subscription & Billing
A1: S/N | B1: Test Scenario | C1: Status | D1: Comment | F1: CASPAA — Web / PWA
A2: 1 | B2: Verify that the owner can see their current plan, its price and the renewal date. | C2: Not-Executed | F2: Total test scenarios | G2: Pass | H2: Fail | I2: Blocker | J2: Not-Executed
A3: 2 | B3: Verify that the plan table shows what the current tier includes and what the tier above adds. | C3: Not-Executed | F3: =COUNTA(B2:B22) | G3: =COUNTIF(C2:C22,"Passed") | H3: =COUNTIF(C2:C22,"Failed") | I3: =COUNTIF(C2:C22,"Blocker") | J3: =COUNTIF(C2:C22,"Not-Executed")
A4: 3 | B4: Verify that an upgrade quotes a pro-rata amount for the days remaining in the period. | C4: Not-Executed
A5: 4 | B5: Verify that the pro-rata amount is proportional to days remaining, not the full month. | C5: Not-Executed
A6: 5 | B6: Verify that paying the upgrade invoice widens entitlements immediately with no re-login. | C6: Not-Executed
A7: 6 | B7: Verify that a zero-cost upgrade completes without a payment gateway trip. | C7: Not-Executed
A8: 7 | B8: Verify that a downgrade is scheduled for the renewal date and is not applied on the spot. | C8: Not-Executed
A9: 8 | B9: Verify that all current-tier features remain usable until the downgrade takes effect. | C9: Not-Executed
A10: 9 | B10: Verify that a downgrade never produces a refund or a credit balance. | C10: Not-Executed
A11: 10 | B11: Verify that the pending plan change and its effective date stay visible until it applies. | C11: Not-Executed
A12: 11 | B12: Verify that a scheduled change can be cancelled with no charge or credit side effect. | C12: Not-Executed
A13: 12 | B13: Verify that the downgrade warning lists only tier-derived features, excluding per-school overrides. | C13: Not-Executed
A14: 13 | B14: Verify that auto-renew can be switched off and access continues to the end of the paid period. | C14: Not-Executed
A15: 14 | B15: Verify that a renewal due in 30 days or fewer shows an amber chip on the owner's dashboard. | C15: Not-Executed
... A22: 21 | B22: Verify that every plan change, payment and auto-renew toggle writes an audit log entry. | C22: Not-Executed

Sheet Multi-branch & Entitlements
A1: S/N | B1: Test Scenario | C1: Status | D1: Comment | F1: CASPAA — Web / PWA
A2: 1 | B2: Verify that a standalone school can be promoted to group HQ when the multibranch entitlement is on. | C2: Not-Executed | F2: Total test scenarios | G2: Pass | H2: Fail | I2: Blocker | J2: Not-Executed
A3: 2 | B3: Verify that the Branches navigation is hidden when the multibranch entitlement is off. | C3: Not-Executed | F3: =COUNTA(B2:B17) | G3: =COUNTIF(C2:C17,"Passed") | H3: =COUNTIF(C2:C17,"Failed") | I3: =COUNTIF(C2:C17,"Blocker") | J3: =COUNTIF(C2:C17,"Not-Executed")
A4: 3 | B4: Verify that group overview totals equal the sum of the individual branch figures. | C4: Not-Executed
A5: 4 | B5: Verify that a group owner can switch into any branch and operate it normally. | C5: Not-Executed
A6: 5 | B6: Verify that no data leaks between branches after a branch switch. | C6: Not-Executed
A7: 6 | B7: Verify that a newly added branch starts empty and fully isolated. | C7: Not-Executed
A8: 7 | B8: Verify that the group layer stays available while the owner is switched into a branch. | C8: Not-Executed
A9: 8 | B9: Verify that features included in the plan tier are visible by default. | C9: Not-Executed
A10: 9 | B10: Verify that a per-school override switches a feature on immediately. | C10: Not-Executed
A11: 10 | B11: Verify that a per-school removal hides a feature the plan would otherwise include. | C11: Not-Executed
A12: 11 | B12: Verify that an unentitled module is hidden from the navigation entirely. | C12: Not-Executed
A13: 12 | B13: Verify that deep-linking to an unentitled view shows a locked screen with an upgrade path. | C13: Not-Executed
A14: 13 | B14: Verify that requesting a feature from the locked screen raises a ticket in the COP support desk. | C14: Not-Executed
A15: 14 | B15: Verify that the requesting school can see that same ticket in their own Help and Support. | C15: Not-Executed
... A17: 16 | B17: Verify that a global platform flag switched off overrides any per-school override. | C17: Not-Executed

Sheet Notifications
A1: S/N | B1: Test Scenario | C1: Status | D1: Comment | F1: CASPAA — Web / PWA
A2: 1 | B2: Verify that the school can select the default channels used for outbound notifications. | C2: Not-Executed | F2: Total test scenarios | G2: Pass | H2: Fail | I2: Blocker | J2: Not-Executed
A3: 2 | B3: Verify that the SMS channel is rendered disabled and cannot be switched on. | C3: Not-Executed | F3: =COUNTA(B2:B16) | G3: =COUNTIF(C2:C16,"Passed") | H3: =COUNTIF(C2:C16,"Failed") | I3: =COUNTIF(C2:C16,"Blocker") | J3: =COUNTIF(C2:C16,"Not-Executed")
A4: 3 | B4: Verify that the reason SMS is unavailable is stated on screen rather than left blank. | C4: Not-Executed
A5: 4 | B5: Verify that disabling a channel stops every module from using it. | C5: Not-Executed
A6: 5 | B6: Verify that switching a trigger off stops that notification on all channels. | C6: Not-Executed
A7: 6 | B7: Verify that the sickbay send-home alert fires even with every trigger switched off. | C7: Not-Executed
A8: 7 | B8: Verify that a parent receives notifications relating only to their own children. | C8: Not-Executed
A9: 8 | B9: Verify that an in-app notification is written even when an external channel fails. | C9: Not-Executed
A10: 9 | B10: Verify that the bell unread count matches the number of genuinely unread items. | C10: Not-Executed
A11: 10 | B11: Verify that opening a notification clears the unread state of that item only. | C11: Not-Executed
A12: 11 | B12: Verify that opening a notification deep-links to the relevant record. | C12: Not-Executed
A13: 12 | B13: Verify that a delivery failure is logged and never fails the originating business action. | C13: Not-Executed
A14: 13 | B14: Verify that the same trigger for the same target on the same day sends only once. | C14: Not-Executed
A15: 14 | B15: Verify that notifications queued offline dispatch on reconnect without duplicating. | C15: Not-Executed
A16: 15 | B16: Verify that no notification body contains another family's data. | C16: Not-Executed

Sheet Offline & PWA
A1: S/N | B1: Test Scenario | C1: Status | D1: Comment | F1: CASPAA — Web / PWA
A2: 1 | B2: Verify that the app can be installed to the device home screen from the browser. | C2: Not-Executed | F2: Total test scenarios | G2: Pass | H2: Fail | I2: Blocker | J2: Not-Executed
A3: 2 | B3: Verify that the installed app launches with the school's own branding and icon. | C3: Not-Executed | F3: =COUNTA(B2:B14) | G3: =COUNTIF(C2:C14,"Passed") | H3: =COUNTIF(C2:C14,"Failed") | I3: =COUNTIF(C2:C14,"Blocker") | J3: =COUNTIF(C2:C14,"Not-Executed")
A4: 3 | B4: Verify that the app loads and renders while the device is fully offline. | C4: Not-Executed
A5: 4 | B5: Verify that a clear offline indicator is shown as soon as connectivity is lost. | C5: Not-Executed
A6: 5 | B6: Verify that attendance can be marked while offline. | C6: Not-Executed
A7: 6 | B7: Verify that offline changes sync automatically once connectivity returns. | C7: Not-Executed
A8: 7 | B8: Verify that no data is lost when the app is closed with offline changes still pending. | C8: Not-Executed
A9: 8 | B9: Verify that a sync conflict resolves by the documented rule and is recorded in the audit log. | C9: Not-Executed
A10: 9 | B10: Verify that payment records survive an offline to online transition with zero loss. | C10: Not-Executed
A11: 10 | B11: Verify that the dashboard shows last-known figures with an offline last-updated marker. | C11: Not-Executed
A12: 11 | B12: Verify that actions requiring connectivity are disabled with an explanation while offline. | C12: Not-Executed
A13: 12 | B13: Verify that a service worker update does not discard unsynced local data. | C13: Not-Executed
A14: 13 | B14: Verify that the app recovers correctly after connectivity drops mid-submission. | C14: Not-Executed

Sheet Usability
A1: S/N | B1: Test Scenario | C1: Status | D1: Comment | F1: CASPAA — Web / PWA
A2: 1 | B2: Verify that users can navigate between screens and modules without confusion. | C2: Not-Executed | F2: Total test scenarios | G2: Pass | H2: Fail | I2: Blocker | J2: Not-Executed
A3: 2 | B3: Check for consistent design elements like fonts, colours and button styles throughout the app. | C3: Not-Executed | F3: =COUNTA(B2:B21) | G3: =COUNTIF(C2:C21,"Passed") | H3: =COUNTIF(C2:C21,"Failed") | I3: =COUNTIF(C2:C21,"Blocker") | J3: =COUNTIF(C2:C21,"Not-Executed")
A4: 3 | B4: Ensure that the placement of buttons, icons and menus feels natural and intuitive. | C4: Not-Executed
A5: 4 | B5: Verify that error messages are clear, helpful and guide the user to resolve the issue. | C5: Not-Executed
A6: 5 | B6: Ensure text and background colours meet accessibility contrast standards. | C6: Not-Executed
A7: 6 | B7: Verify that status is never communicated by colour alone. | C7: Not-Executed
A8: 7 | B8: Verify that font sizes adjust correctly when the user changes device text size settings. | C8: Not-Executed
A9: 8 | B9: Verify that every form input has an associated visible label. | C9: Not-Executed
A10: 9 | B10: Verify that users can easily access help and support when needed. | C10: Not-Executed
A11: 10 | B11: Test the ease of creating, logging into and managing user accounts. | C11: Not-Executed
A12: 11 | B12: Verify that touch inputs, swipes and gestures are responsive and smooth. | C12: Not-Executed
A13: 12 | B13: Verify that users receive immediate feedback for actions like button presses or submissions. | C13: Not-Executed
A14: 13 | B14: Ensure loading spinners or progress bars appear during data loading or processing. | C14: Not-Executed
A15: 14 | B15: Test the ease of applying and removing filters or sorting options on data tables. | C15: Not-Executed
... A21: 20 | B21: Verify that the app is usable and legible on a small mid-range phone screen. | C21: Not-Executed

Sheet Test Cases (Detailed)
A1: Test Case ID | B1: Module | C1: Title / Objective | D1: Priority | E1: Type | F1: Preconditions | G1: Test Steps | H1: Test Data | I1: Expected Result | J1: Actual Result | K1: Status | L1: Comment
A2: TC_AUTH_001 | B2: Auth & Tenancy | C2: Role-aware login routes each user to the correct portal | D2: High | E2: Functional | F2: A school exists and is Active. An owner, teacher and parent account each exist for it. | G2: 1. Open the school's CASPAA URL. 2. Enter the owner's email and password. 3. Tap Sign in. 4. Sign out. 5. Repeat steps 2-3 with the teacher account, then the parent account. | H2: owner@school.test / Passw0rd! teacher@school.test / Passw0rd! parent@school.test / Passw0rd! | I2: Owner lands on the admin dashboard with the full nav. Teacher lands on the teacher dashboard with no finance nav. Parent lands on the parent dashboard showing only their own children. | K2: Not-Executed
A3: TC_AUTH_002 | B3: Auth & Tenancy | C3: Cross-tenant data isolation is enforced | D3: High | E3: Security | F3: Two schools exist, School A and School B, each with students. | G3: 1. Sign in as the School A admin. 2. Copy a student record ID belonging to School B. 3. Deep-link to the student detail view using School B's student ID. 4. Observe the response. | H3: School A admin account. School B student ID: stu_b_0001 | I3: The record is not returned. A not-found or access-denied screen is shown. No School B data appears anywhere in the response, and the attempt is written to the audit log. | K3: Not-Executed
A4: TC_AUTH_003 | B4: Auth & Tenancy | C4: Verification gate blocks an unverified proprietor | D4: High | E4: Negative | F4: A proprietor has self-registered and uploaded a document. Verification status is pending. | G4: 1. Sign in as the pending proprietor. 2. Observe the landing screen. 3. Attempt to deep-link directly to the admin dashboard URL. 4. Attempt to deep-link to the finance view. | H4: pending.proprietor@school.test | I4: The verification screen renders on every attempt. School name, official email and submitted documents are shown. No dashboard or module view is reachable by any deep link. Sign out remains available. | K4: Not-Executed
A5: TC_STU_001 | B5: Students & Admissions | C5: Duplicate admission number is rejected | D5: High | E5: Negative | F5: A student already exists with admission number ADM/2026/001. | G5: 1. Sign in as admin. 2. Go to Students and select Add Student. 3. Complete all required fields. 4. Enter admission number ADM/2026/001. 5. Tap Save. | H5: Name: Test Child Class: JSS1A Admission no: ADM/2026/001 | I5: A validation error is shown stating the admission number is already in use. The student is not created. No partial record is written. | K5: Not-Executed
A6: TC_STU_002 | B6: Students & Admissions | C6: New student propagates to roster, attendance and fees | D6: High | E6: Functional | F6: A class JSS1A exists with an active fee structure for the current term. | G6: 1. Add a new student to JSS1A with a linked parent. 2. Save. 3. Open Academic > Classes > JSS1A roster. 4. Open Attendance and select JSS1A. 5. Open Finance > Invoices and filter to JSS1A. 6. Sign in as the linked parent. | H6: Name: Ada Obi Class: JSS1A Parent: parent@school.test | I6: The student appears in the roster, in the attendance register and in the fee module immediately. The linked parent receives an in-app notification and sees the child on their dashboard. | K6: Not-Executed
A7: TC_STU_003 | B7: Students & Admissions | C7: Bulk CSV import is transactional per row | D7: Medium | E7: Functional | F7: Admin has a CSV of 10 students where rows 4 and 7 are invalid (missing class, duplicate admission number). | G7: 1. Go to Students > Bulk Import CSV. 2. Upload the prepared CSV. 3. Review the preview screen. 4. Confirm the import. 5. Check the resulting student list. | H7: students_10rows.csv (rows 4 and 7 invalid) | I7: The preview flags rows 4 and 7 with a specific reason each. On confirm, 8 students are imported and 2 are reported as skipped. The valid rows are unaffected by the invalid ones. | K7: Not-Executed
A8: TC_ATT_001 | B8: Attendance | C8: Absence triggers a same-day parent alert | D8: High | E8: Functional | F8: Teacher is assigned to JSS1A. At least one student in JSS1A has a linked parent. The absence trigger is enabled. | G8: 1. Sign in as the class teacher. 2. Open Attendance and select JSS1A. 3. Toggle one student to Absent. 4. Submit the register. 5. Sign in as that student's parent. 6. Open the notification bell. | H8: Class: JSS1A Student: Ada Obi | I8: The register saves. The parent of the absent student receives a notification the same day naming the child and the date. Parents of present students receive nothing. | K8: Not-Executed
A9: TC_ATT_002 | B9: Attendance | C9: Offline attendance syncs without duplicating | D9: High | E9: Functional | F9: The PWA is installed. Teacher is signed in and assigned to JSS1A. | G9: 1. Put the device into airplane mode. 2. Open Attendance for JSS1A. 3. Mark two students Absent and submit. 4. Confirm the offline indicator and queued state. 5. Restore connectivity. 6. Wait for sync, then reload the register. | H9: Class: JSS1A, today's date | I9: The register submits and is queued offline. On reconnect it syncs automatically. Exactly one attendance record exists for that class and date, with both absences intact and parent alerts sent once. | K9: Not-Executed
A10: TC_ATT_003 | B10: Attendance | C10: Duplicate submission for the same day is prevented | D10: Medium | E10: Negative | F10: Attendance for JSS1A has already been submitted for today. | G10: 1. Sign in as the class teacher. 2. Open Attendance and select JSS1A for today. 3. Attempt to change a status and submit again. | H10: Class: JSS1A, today's date | I10: The register is locked for that day. Re-submission is blocked with a clear message directing the teacher to request an admin override. No second record is created. | K10: Not-Executed
A11: TC_RES_001 | B11: Results & Reporting | C11: Unapproved results are invisible to parents and students | D11: High | E11: Security | F11: A teacher has entered but not submitted results for JSS1A Mathematics. | G11: 1. Sign in as the teacher and enter CA and exam scores for JSS1A Mathematics. 2. Submit for approval. 3. Sign in as a JSS1A parent and open Results. 4. Sign in as a JSS1A student and open My Results. 5. Attempt to deep-link to the result record ID as the parent. | H11: Class: JSS1A Subject: Mathematics CA: 28, Exam: 55 | I11: Neither parent nor student sees any score. An amber pending banner is displayed instead. The deep link returns no result data. | K11: Not-Executed
A12: TC_RES_002 | B12: Results & Reporting | C12: Approval requires a comment for every student | D12: High | E12: Negative | F12: Results for JSS1A Mathematics are submitted and pending approval. 20 students, 19 have comments. | G12: 1. Sign in as admin. 2. Open Academic > Results and select the pending JSS1A Mathematics broadsheet. 3. Leave one student without a comment. 4. Attempt to tap Approve. 5. Add the missing comment. 6. Tap Approve. | H12: Class: JSS1A, 20 students | I12: Approve is disabled while any comment is missing, with the reason shown. Once the last comment is added, Approve becomes enabled and succeeds. Parents and students are notified exactly once. | K12: Not-Executed
A13: TC_RES_003 | B13: Results & Reporting | C13: Tied averages share a rank and the next rank skips | D13: Medium | E13: Functional | F13: Results are entered for a class where two students share an identical average. | G13: 1. Enter results producing averages: 82, 78, 78, 71. 2. Submit and approve. 3. Open the broadsheet. 4. Open the report card of each of the two tied students. | H13: Averages: 82, 78, 78, 71 | I13: Ranks read 1, 2, 2, 4. The two tied students both show rank 2. Rank 3 is skipped. Each report card shows the same rank as the broadsheet. | K13: Not-Executed
... A33: TC_OFF_001 | B33: Offline & PWA | C33: App is installable and functions offline | D33: High | E33: Functional | F33: The school URL is reachable and the user has signed in at least once online. | G33: 1. Open the school URL in a supported browser. 2. Install the app to the home screen. 3. Confirm the icon and name. 4. Enable airplane mode. 5. Launch the installed app. 6. Navigate between dashboard, students and attendance. | H33: Chrome / Edge on Android or desktop | I33: The install prompt appears and installation succeeds with the school's branding. The app launches offline, renders cached data, shows a clear offline indicator, and connectivity-dependent actions are disabled with an explanation. | K33: Not-Executed
